Workbook

Sheet Leave Tracker
A1: Employee ID | B1: Name | C1: Leave Type | D1: Start Date | E1: End Date | F1: Number of Days | G1: Rejoining Date | H1: Leave Status | I1: Status as on | J1: Leave Balance | K1: Current Leave Balance | L1: Sort Order | M1: Filter Leave Type: | N1: Rejoin alert | O1: Extende Days | P1: Remanrk
A2: 2120 | B2: =IFERROR(VLOOKUP(A2,'[1]Master File'!$A$2:$C$312,3,0)," ") -> Siraj Ahmad | C2: Annual Leave | D2: 45607 | E2: 45667 | F2: =IF(OR(D2="",E2 =""), "", E2 - D2+ 1) -> 61 | G2: 45672 | H2: =IF(G2="", "Not Rejoined", "Rejoined") -> Rejoined | I2: =IF(AND(G2="", E2="", D2=""), "", IF(D2>TODAY(), "Applied", IF(G2<>"", IF(G2<E2, "Early Rejoin", "Rejoined"), IF(E2>TODAY(), "On Leave", "Not Rejoined")))) -> Rejoined | L2: =IF(H2="Not Rejoined", 0, 1) -> 1 | M2: =IF(OR(#REF!="", C2=#REF!), 1, 0) -> #REF! | N2: =IF(AND(E2<>"", E2>=TODAY(), E2<=TODAY()+3), "Rejoin Follow Up", "") | O2: =IF(AND(G2<>"", G2 > E2, (G2 - E2) <> 1), G2 - E2, "") -> 5
A3: 2554 | B3: =IFERROR(VLOOKUP(A3,'[1]Master File'!$A$2:$C$312,3,0)," ") -> Sheikh Shahid | C3: Annual Leave | D3: 45611 | E3: 45670 | F3: =IF(OR(D3="",E3 =""), "", E3 - D3+ 1) -> 60 | G3: 45672 | I3: =IF(AND(G3="", E3="", D3=""), "", IF(D3>TODAY(), "Applied", IF(G3<>"", IF(G3<E3, "Early Rejoin", "Rejoined"), IF(E3>TODAY(), "On Leave", "Not Rejoined")))) -> Rejoined | N3: =IF(AND(E3<>"", E3>=TODAY(), E3<=TODAY()+3), "Rejoin Follow Up", "") | O3: =IF(AND(G3<>"", G3 > E3, (G3 - E3) <> 1), G3 - E3, "") -> 2
A4: 232 | B4: =IFERROR(VLOOKUP(A4,'[1]Master File'!$A$2:$C$312,3,0)," ") -> Ruhul Amin Haian Saiyal | C4: Annual Leave | D4: 45613 | E4: 45672 | F4: =IF(OR(D4="",E4 =""), "", E4 - D4+ 1) -> 60 | G4: 45676 | H4: =IF(G4="", "Not Rejoined", "Rejoined") -> Rejoined | I4: =IF(AND(G4="", E4="", D4=""), "", IF(D4>TODAY(), "Applied", IF(G4<>"", IF(G4<E4, "Early Rejoin", "Rejoined"), IF(E4>TODAY(), "On Leave", "Not Rejoined")))) -> Rejoined | J4: =IFERROR(VLOOKUP(A4,'[1]Master File'!$A$2:$Q$312,17,0)," ") -> 74.5 | K4: =IF(C4="Annual Leave",J4-F4," ") -> 14.5 | L4: =IF(H4="Not Rejoined", 0, 1) -> 1 | M4: =IF(OR(#REF!="", C4=#REF!), 1, 0) -> #REF! | N4: =IF(AND(E4<>"", E4>=TODAY(), E4<=TODAY()+3), "Rejoin Follow Up", "") | O4: =IF(AND(G4<>"", G4 > E4, (G4 - E4) <> 1), G4 - E4, "") -> 4
A5: 2450 | B5: =IFERROR(VLOOKUP(A5,'[1]Master File'!$A$2:$C$312,3,0)," ") -> Najir Hussain | C5: Annual Leave | D5: 45614 | E5: 45673 | F5: =IF(OR(D5="",E5 =""), "", E5 - D5+ 1) -> 60 | G5: 45677 | H5: =IF(G5="", "Not Rejoined", "Rejoined") -> Rejoined | I5: =IF(AND(G5="", E5="", D5=""), "", IF(D5>TODAY(), "Applied", IF(G5<>"", IF(G5<E5, "Early Rejoin", "Rejoined"), IF(E5>TODAY(), "On Leave", "Not Rejoined")))) -> Rejoined | L5: =IF(H5="Not Rejoined", 0, 1) -> 1 | M5: =IF(OR(#REF!="", C5=#REF!), 1, 0) -> #REF! | N5: =IF(AND(E5<>"", E5>=TODAY(), E5<=TODAY()+3), "Rejoin Follow Up", "") | O5: =IF(AND(G5<>"", G5 > E5, (G5 - E5) <> 1), G5 - E5, "") -> 4
A6: 1806 | B6: =IFERROR(VLOOKUP(A6,'[1]Master File'!$A$2:$C$312,3,0)," ") -> Saroj Kumar Mukhram | C6: Annual Leave | D6: 45614 | E6: 45673 | F6: =IF(OR(D6="",E6 =""), "", E6 - D6+ 1) -> 60 | G6: 45677 | I6: =IF(AND(G6="", E6="", D6=""), "", IF(D6>TODAY(), "Applied", IF(G6<>"", IF(G6<E6, "Early Rejoin", "Rejoined"), IF(E6>TODAY(), "On Leave", "Not Rejoined")))) -> Rejoined | N6: =IF(AND(E6<>"", E6>=TODAY(), E6<=TODAY()+3), "Rejoin Follow Up", "") | O6: =IF(AND(G6<>"", G6 > E6, (G6 - E6) <> 1), G6 - E6, "") -> 4
A7: 2628 | B7: =IFERROR(VLOOKUP(A7,'[1]Master File'!$A$2:$C$312,3,0)," ") -> Sona Kizhakudan Prince | C7: Annual Leave | D7: 45622 | E7: 45660 | F7: =IF(OR(D7="",E7 =""), "", E7 - D7+ 1) -> 39 | G7: 45660 | I7: =IF(AND(G7="", E7="", D7=""), "", IF(D7>TODAY(), "Applied", IF(G7<>"", IF(G7<E7, "Early Rejoin", "Rejoined"), IF(E7>TODAY(), "On Leave", "Not Rejoined")))) -> Rejoined | N7: =IF(AND(E7<>"", E7>=TODAY(), E7<=TODAY()+3), "Rejoin Follow Up", "") | O7: =IF(AND(G7<>"", G7 > E7, (G7 - E7) <> 1), G7 - E7, "")
A8: 2615 | B8: =IFERROR(VLOOKUP(A8,'[1]Master File'!$A$2:$C$312,3,0)," ") -> Qamar Zaman Muhammad Akmal | C8: Annual Leave | D8: 45629 | E8: 45674 | F8: =IF(OR(D8="",E8 =""), "", E8 - D8+ 1) -> 46 | G8: 45681 | I8: =IF(AND(G8="", E8="", D8=""), "", IF(D8>TODAY(), "Applied", IF(G8<>"", IF(G8<E8, "Early Rejoin", "Rejoined"), IF(E8>TODAY(), "On Leave", "Not Rejoined")))) -> Rejoined | N8: =IF(AND(E8<>"", E8>=TODAY(), E8<=TODAY()+3), "Rejoin Follow Up", "") | O8: =IF(AND(G8<>"", G8 > E8, (G8 - E8) <> 1), G8 - E8, "") -> 7
A9: 2599 | B9: =IFERROR(VLOOKUP(A9,'[1]Master File'!$A$2:$C$312,3,0)," ") -> Abdul Rahman | C9: Annual Leave | D9: 45630 | E9: 45675 | F9: =IF(OR(D9="",E9 =""), "", E9 - D9+ 1) -> 46 | G9: 45677 | I9: =IF(AND(G9="", E9="", D9=""), "", IF(D9>TODAY(), "Applied", IF(G9<>"", IF(G9<E9, "Early Rejoin", "Rejoined"), IF(E9>TODAY(), "On Leave", "Not Rejoined")))) -> Rejoined | N9: =IF(AND(E9<>"", E9>=TODAY(), E9<=TODAY()+3), "Rejoin Follow Up", "") | O9: =IF(AND(G9<>"", G9 > E9, (G9 - E9) <> 1), G9 - E9, "") -> 2
A10: 1016 | B10: =IFERROR(VLOOKUP(A10,'[1]Master File'!$A$2:$C$312,3,0)," ") -> Mohammed Abul Hasan | C10: Annual Leave | D10: 45635 | E10: 45694 | F10: =IF(OR(D10="",E10 =""), "", E10 - D10+ 1) -> 60 | G10: 45701 | H10: =IF(G10="", "Not Rejoined", "Rejoined") -> Rejoined | I10: =IF(AND(G10="", E10="", D10=""), "", IF(D10>TODAY(), "Applied", IF(G10<>"", IF(G10<E10, "Early Rejoin", "Rejoined"), IF(E10>TODAY(), "On Leave", "Not Rejoined")))) -> Rejoined | L10: =IF(H10="Not Rejoined", 0, 1) -> 1 | M10: =IF(OR(#REF!="", C10=#REF!), 1, 0) -> #REF! | N10: =IF(AND(E10<>"", E10>=TODAY(), E10<=TODAY()+3), "Rejoin Follow Up", "") | O10: =IF(AND(G10<>"", G10 > E10, (G10 - E10) <> 1), G10 - E10, "") -> 7
A11: 2635 | B11: =IFERROR(VLOOKUP(A11,'[1]Master File'!$A$2:$C$312,3,0)," ") -> Muhamed Minhaj Nayarkandy | C11: Annual Leave | D11: 45635 | E11: 45664 | F11: =IF(OR(D11="",E11 =""), "", E11 - D11+ 1) -> 30 | G11: 45673 | I11: =IF(AND(G11="", E11="", D11=""), "", IF(D11>TODAY(), "Applied", IF(G11<>"", IF(G11<E11, "Early Rejoin", "Rejoined"), IF(E11>TODAY(), "On Leave", "Not Rejoined")))) -> Rejoined | N11: =IF(AND(E11<>"", E11>=TODAY(), E11<=TODAY()+3), "Rejoin Follow Up", "") | O11: =IF(AND(G11<>"", G11 > E11, (G11 - E11) <> 1), G11 - E11, "") -> 9
A12: 2538 | B12: =IFERROR(VLOOKUP(A12,'[1]Master File'!$A$2:$C$312,3,0)," ") -> Rasel Iman Hossain | C12: Annual Leave | D12: 45642 | E12: 45701 | F12: =IF(OR(D12="",E12 =""), "", E12 - D12+ 1) -> 60 | G12: 45709 | I12: =IF(AND(G12="", E12="", D12=""), "", IF(D12>TODAY(), "Applied", IF(G12<>"", IF(G12<E12, "Early Rejoin", "Rejoined"), IF(E12>TODAY(), "On Leave", "Not Rejoined")))) -> Rejoined | N12: =IF(AND(E12<>"", E12>=TODAY(), E12<=TODAY()+3), "Rejoin Follow Up", "") | O12: =IF(AND(G12<>"", G12 > E12, (G12 - E12) <> 1), G12 - E12, "") -> 8
A13: 2614 | B13: =IFERROR(VLOOKUP(A13,'[1]Master File'!$A$2:$C$312,3,0)," ") -> Manish Kumar Yadav | C13: Emergency Leave | D13: 45656 | E13: 45702 | F13: =IF(OR(D13="",E13 =""), "", E13 - D13+ 1) -> 47 | G13: 45726 | I13: =IF(AND(G13="", E13="", D13=""), "", IF(D13>TODAY(), "Applied", IF(G13<>"", IF(G13<E13, "Early Rejoin", "Rejoined"), IF(E13>TODAY(), "On Leave", "Not Rejoined")))) -> Rejoined | N13: =IF(AND(E13<>"", E13>=TODAY(), E13<=TODAY()+3), "Rejoin Follow Up", "") | O13: =IF(AND(G13<>"", G13 > E13, (G13 - E13) <> 1), G13 - E13, "") -> 24
A14: 1106 | B14: =IFERROR(VLOOKUP(A14,'[1]Master File'!$A$2:$C$312,3,0)," ") -> Ram Chandra Pradhan | C14: Annual Leave | D14: 45656 | E14: 45715 | F14: =IF(OR(D14="",E14 =""), "", E14 - D14+ 1) -> 60 | G14: 45716 | I14: =IF(AND(G14="", E14="", D14=""), "", IF(D14>TODAY(), "Applied", IF(G14<>"", IF(G14<E14, "Early Rejoin", "Rejoined"), IF(E14>TODAY(), "On Leave", "Not Rejoined")))) -> Rejoined | N14: =IF(AND(E14<>"", E14>=TODAY(), E14<=TODAY()+3), "Rejoin Follow Up", "") | O14: =IF(AND(G14<>"", G14 > E14, (G14 - E14) <> 1), G14 - E14, "")
A15: 999 | B15: =IFERROR(VLOOKUP(A15,'[1]Master File'!$A$2:$C$312,3,0)," ") -> Gul Meen Khan Lal Meer Khan | C15: Annual Leave | D15: 45656 | E15: 45715 | F15: =IF(OR(D15="",E15 =""), "", E15 - D15+ 1) -> 60 | G15: 45775 | I15: =IF(AND(G15="", E15="", D15=""), "", IF(D15>TODAY(), "Applied", IF(G15<>"", IF(G15<E15, "Early Rejoin", "Rejoined"), IF(E15>TODAY(), "On Leave", "Not Rejoined")))) -> Rejoined | N15: =IF(AND(E15<>"", E15>=TODAY(), E15<=TODAY()+3), "Rejoin Follow Up", "") | O15: =IF(AND(G15<>"", G15 > E15, (G15 - E15) <> 1), G15 - E15, "") -> 60
A16: 2610 | B16: =IFERROR(VLOOKUP(A16,'[1]Master File'!$A$2:$C$312,3,0)," ") -> Natalia Kolieva | C16: Annual Leave | D16: 45656 | E16: 45660 | F16: =IF(OR(D16="",E16 =""), "", E16 - D16+ 1) -> 5 | G16: 45661 | I16: =IF(AND(G16="", E16="", D16=""), "", IF(D16>TODAY(), "Applied", IF(G16<>"", IF(G16<E16, "Early Rejoin", "Rejoined"), IF(E16>TODAY(), "On Leave", "Not Rejoined")))) -> Rejoined | N16: =IF(AND(E16<>"", E16>=TODAY(), E16<=TODAY()+3), "Rejoin Follow Up", "") | O16: =IF(AND(G16<>"", G16 > E16, (G16 - E16) <> 1), G16 - E16, "")
A17: 67 | B17: =IFERROR(VLOOKUP(A17,'[1]Master File'!$A$2:$C$312,3,0)," ") -> Esoj Jose | C17: Annual Leave | D17: 45659 | E17: 45688 | F17: =IF(OR(D17="",E17 =""), "", E17 - D17+ 1) -> 30 | G17: 45691 | I17: =IF(AND(G17="", E17="", D17=""), "", IF(D17>TODAY(), "Applied", IF(G17<>"", IF(G17<E17, "Early Rejoin", "Rejoined"), IF(E17>TODAY(), "On Leave", "Not Rejoined")))) -> Rejoined | N17: =IF(AND(E17<>"", E17>=TODAY(), E17<=TODAY()+3), "Rejoin Follow Up", "") | O17: =IF(AND(G17<>"", G17 > E17, (G17 - E17) <> 1), G17 - E17, "") -> 3
A18: 2240 | B18: =IFERROR(VLOOKUP(A18,'[1]Master File'!$A$2:$C$312,3,0)," ") -> Rifas Ansary Mohammed | C18: Annual Leave | D18: 45663 | E18: 45666 | F18: =IF(OR(D18="",E18 =""), "", E18 - D18+ 1) -> 4 | G18: 45667 | I18: =IF(AND(G18="", E18="", D18=""), "", IF(D18>TODAY(), "Applied", IF(G18<>"", IF(G18<E18, "Early Rejoin", "Rejoined"), IF(E18>TODAY(), "On Leave", "Not Rejoined")))) -> Rejoined | N18: =IF(AND(E18<>"", E18>=TODAY(), E18<=TODAY()+3), "Rejoin Follow Up", "") | O18: =IF(AND(G18<>"", G18 > E18, (G18 - E18) <> 1), G18 - E18, "")
A19: 2665 | B19: =IFERROR(VLOOKUP(A19,'[1]Master File'!$A$2:$C$312,3,0)," ") -> Manmeet Singh | C19: Emergency Leave | D19: 45666 | E19: 45677 | F19: =IF(OR(D19="",E19 =""), "", E19 - D19+ 1) -> 12 | I19: Overstay | N19: =IF(AND(E19<>"", E19>=TODAY(), E19<=TODAY()+3), "Rejoin Follow Up", "") | O19: =IF(AND(G19<>"", G19 > E19, (G19 - E19) <> 1), G19 - E19, "")
A20: 394 | B20: =IFERROR(VLOOKUP(A20,'[1]Master File'!$A$2:$C$312,3,0)," ") -> Kamal Hossain Tofazzal Mollah | C20: Annual Leave | D20: 45669 | E20: 45730 | F20: =IF(OR(D20="",E20 =""), "", E20 - D20+ 1) -> 62 | G20: 45730 | I20: =IF(AND(G20="", E20="", D20=""), "", IF(D20>TODAY(), "Applied", IF(G20<>"", IF(G20<E20, "Early Rejoin", "Rejoined"), IF(E20>TODAY(), "On Leave", "Not Rejoined")))) -> Rejoined | N20: =IF(AND(E20<>"", E20>=TODAY(), E20<=TODAY()+3), "Rejoin Follow Up", "") | O20: =IF(AND(G20<>"", G20 > E20, (G20 - E20) <> 1), G20 - E20, "")
A21: 2647 | B21: =IFERROR(VLOOKUP(A21,'[1]Master File'!$A$2:$C$312,3,0)," ") -> Sethu Kumar | C21: Annual Leave | D21: 45670 | E21: 45687 | F21: =IF(OR(D21="",E21 =""), "", E21 - D21+ 1) -> 18 | G21: 45688 | I21: =IF(AND(G21="", E21="", D21=""), "", IF(D21>TODAY(), "Applied", IF(G21<>"", IF(G21<E21, "Early Rejoin", "Rejoined"), IF(E21>TODAY(), "On Leave", "Not Rejoined")))) -> Rejoined | N21: =IF(AND(E21<>"", E21>=TODAY(), E21<=TODAY()+3), "Rejoin Follow Up", "") | O21: =IF(AND(G21<>"", G21 > E21, (G21 - E21) <> 1), G21 - E21, "")
A22: 1360 | B22: =IFERROR(VLOOKUP(A22,'[1]Master File'!$A$2:$C$312,3,0)," ") -> Buchi Babu Daram | C22: Annual Leave | D22: 45670 | E22: 45684 | F22: =IF(OR(D22="",E22 =""), "", E22 - D22+ 1) -> 15 | G22: 45685 | I22: =IF(AND(G22="", E22="", D22=""), "", IF(D22>TODAY(), "Applied", IF(G22<>"", IF(G22<E22, "Early Rejoin", "Rejoined"), IF(E22>TODAY(), "On Leave", "Not Rejoined")))) -> Rejoined | N22: =IF(AND(E22<>"", E22>=TODAY(), E22<=TODAY()+3), "Rejoin Follow Up", "") | O22: =IF(AND(G22<>"", G22 > E22, (G22 - E22) <> 1), G22 - E22, "")
A23: 2247 | B23: =IFERROR(VLOOKUP(A23,'[1]Master File'!$A$2:$C$312,3,0)," ") -> Ajaya Kumar | C23: Annual Leave | D23: 45670 | E23: 45730 | F23: =IF(OR(D23="",E23 =""), "", E23 - D23+ 1) -> 61 | G23: 45736 | I23: =IF(AND(G23="", E23="", D23=""), "", IF(D23>TODAY(), "Applied", IF(G23<>"", IF(G23<E23, "Early Rejoin", "Rejoined"), IF(E23>TODAY(), "On Leave", "Not Rejoined")))) -> Rejoined | N23: =IF(AND(E23<>"", E23>=TODAY(), E23<=TODAY()+3), "Rejoin Follow Up", "") | O23: =IF(AND(G23<>"", G23 > E23, (G23 - E23) <> 1), G23 - E23, "") -> 6
A24: 2315 | B24: =IFERROR(VLOOKUP(A24,'[1]Master File'!$A$2:$C$312,3,0)," ") -> Mandresh Khedan | C24: Annual Leave | D24: 45670 | E24: 45729 | F24: =IF(OR(D24="",E24 =""), "", E24 - D24+ 1) -> 60 | G24: 45738 | I24: =IF(AND(G24="", E24="", D24=""), "", IF(D24>TODAY(), "Applied", IF(G24<>"", IF(G24<E24, "Early Rejoin", "Rejoined"), IF(E24>TODAY(), "On Leave", "Not Rejoined")))) -> Rejoined | N24: =IF(AND(E24<>"", E24>=TODAY(), E24<=TODAY()+3), "Rejoin Follow Up", "") | O24: =IF(AND(G24<>"", G24 > E24, (G24 - E24) <> 1), G24 - E24, "") -> 9
A25: 14 | B25: =IFERROR(VLOOKUP(A25,'[1]Master File'!$A$2:$C$312,3,0)," ") -> Afroz Ali Khan Khan | C25: Annual Leave | D25: 45670 | E25: 45678 | F25: =IF(OR(D25="",E25 =""), "", E25 - D25+ 1) -> 9 | G25: 45679 | I25: =IF(AND(G25="", E25="", D25=""), "", IF(D25>TODAY(), "Applied", IF(G25<>"", IF(G25<E25, "Early Rejoin", "Rejoined"), IF(E25>TODAY(), "On Leave", "Not Rejoined")))) -> Rejoined | N25: =IF(AND(E25<>"", E25>=TODAY(), E25<=TODAY()+3), "Rejoin Follow Up", "") | O25: =IF(AND(G25<>"", G25 > E25, (G25 - E25) <> 1), G25 - E25, "")
A26: 2545 | B26: =IFERROR(VLOOKUP(A26,'[1]Master File'!$A$2:$C$312,3,0)," ") -> Mohammad Jamal Badiyar | C26: Annual Leave | D26: 45671 | E26: 45702 | F26: =IF(OR(D26="",E26 =""), "", E26 - D26+ 1) -> 32 | G26: 45708 | I26: =IF(AND(G26="", E26="", D26=""), "", IF(D26>TODAY(), "Applied", IF(G26<>"", IF(G26<E26, "Early Rejoin", "Rejoined"), IF(E26>TODAY(), "On Leave", "Not Rejoined")))) -> Rejoined | N26: =IF(AND(E26<>"", E26>=TODAY(), E26<=TODAY()+3), "Rejoin Follow Up", "") | O26: =IF(AND(G26<>"", G26 > E26, (G26 - E26) <> 1), G26 - E26, "") -> 6
A27: 2737 | B27: Anbu Vadivel Subbiah | C27: Emergency Leave | D27: 45671 | E27: 45678 | F27: =IF(OR(D27="",E27 =""), "", E27 - D27+ 1) -> 8 | G27: 45679 | I27: =IF(AND(G27="", E27="", D27=""), "", IF(D27>TODAY(), "Applied", IF(G27<>"", IF(G27<E27, "Early Rejoin", "Rejoined"), IF(E27>TODAY(), "On Leave", "Not Rejoined")))) -> Rejoined | N27: =IF(AND(E27<>"", E27>=TODAY(), E27<=TODAY()+3), "Rejoin Follow Up", "") | O27: =IF(AND(G27<>"", G27 > E27, (G27 - E27) <> 1), G27 - E27, "")
A28: 2550 | B28: =IFERROR(VLOOKUP(A28,'[1]Master File'!$A$2:$C$312,3,0)," ") -> Grasvin Grogory | C28: Annual Leave | D28: 45677 | E28: 45698 | F28: =IF(OR(D28="",E28 =""), "", E28 - D28+ 1) -> 22 | G28: 45719 | I28: =IF(AND(G28="", E28="", D28=""), "", IF(D28>TODAY(), "Applied", IF(G28<>"", IF(G28<E28, "Early Rejoin", "Rejoined"), IF(E28>TODAY(), "On Leave", "Not Rejoined")))) -> Rejoined | N28: =IF(AND(E28<>"", E28>=TODAY(), E28<=TODAY()+3), "Rejoin Follow Up", "") | O28: =IF(AND(G28<>"", G28 > E28, (G28 - E28) <> 1), G28 - E28, "") -> 21
A29: 835 | B29: =IFERROR(VLOOKUP(A29,'[1]Master File'!$A$2:$C$312,3,0)," ") -> Asim Abbas Sadiq Ali | C29: Annual Leave | D29: 45677 | E29: 45698 | F29: =IF(OR(D29="",E29 =""), "", E29 - D29+ 1) -> 22 | G29: 45699 | I29: =IF(AND(G29="", E29="", D29=""), "", IF(D29>TODAY(), "Applied", IF(G29<>"", IF(G29<E29, "Early Rejoin", "Rejoined"), IF(E29>TODAY(), "On Leave", "Not Rejoined")))) -> Rejoined | N29: =IF(AND(E29<>"", E29>=TODAY(), E29<=TODAY()+3), "Rejoin Follow Up", "") | O29: =IF(AND(G29<>"", G29 > E29, (G29 - E29) <> 1), G29 - E29, "")
A30: 1761 | B30: =IFERROR(VLOOKUP(A30,'[1]Master File'!$A$2:$C$312,3,0)," ") -> Syed Mushtaq Ahamad Syed Mukhtar Ahmed | C30: Annual Leave | D30: 45678 | E30: 45692 | F30: =IF(OR(D30="",E30 =""), "", E30 - D30+ 1) -> 15 | G30: 45693 | I30: =IF(AND(G30="", E30="", D30=""), "", IF(D30>TODAY(), "Applied", IF(G30<>"", IF(G30<E30, "Early Rejoin", "Rejoined"), IF(E30>TODAY(), "On Leave", "Not Rejoined")))) -> Rejoined | N30: =IF(AND(E30<>"", E30>=TODAY(), E30<=TODAY()+3), "Rejoin Follow Up", "") | O30: =IF(AND(G30<>"", G30 > E30, (G30 - E30) <> 1), G30 - E30, "")
A31: 2611 | B31: =IFERROR(VLOOKUP(A31,'[1]Master File'!$A$2:$C$312,3,0)," ") -> Sreejesh Kumar | C31: Annual Leave | D31: 45679 | E31: 45697 | F31: =IF(OR(D31="",E31 =""), "", E31 - D31+ 1) -> 19 | G31: 45699 | I31: =IF(AND(G31="", E31="", D31=""), "", IF(D31>TODAY(), "Applied", IF(G31<>"", IF(G31<E31, "Early Rejoin", "Rejoined"), IF(E31>TODAY(), "On Leave", "Not Rejoined")))) -> Rejoined | N31: =IF(AND(E31<>"", E31>=TODAY(), E31<=TODAY()+3), "Rejoin Follow Up", "") | O31: =IF(AND(G31<>"", G31 > E31, (G31 - E31) <> 1), G31 - E31, "") -> 2
A32: 333 | B32: =IFERROR(VLOOKUP(A32,'[1]Master File'!$A$2:$C$312,3,0)," ") -> Zohirul Islam Nuruzzaman | C32: Annual Leave | D32: 45682 | E32: 45712 | F32: =IF(OR(D32="",E32 =""), "", E32 - D32+ 1) -> 31 | G32: 45713 | I32: =IF(AND(G32="", E32="", D32=""), "", IF(D32>TODAY(), "Applied", IF(G32<>"", IF(G32<E32, "Early Rejoin", "Rejoined"), IF(E32>TODAY(), "On Leave", "Not Rejoined")))) -> Rejoined | N32: =IF(AND(E32<>"", E32>=TODAY(), E32<=TODAY()+3), "Rejoin Follow Up", "") | O32: =IF(AND(G32<>"", G32 > E32, (G32 - E32) <> 1), G32 - E32, "")
A33: 34 | B33: =IFERROR(VLOOKUP(A33,'[1]Master File'!$A$2:$C$312,3,0)," ") -> Ashok Kumar Lekhu Ram | C33: Emergency Leave | D33: 45685 | E33: 45715 | F33: =IF(OR(D33="",E33 =""), "", E33 - D33+ 1) -> 31 | G33: 45721 | I33: =IF(AND(G33="", E33="", D33=""), "", IF(D33>TODAY(), "Applied", IF(G33<>"", IF(G33<E33, "Early Rejoin", "Rejoined"), IF(E33>TODAY(), "On Leave", "Not Rejoined")))) -> Rejoined | N33: =IF(AND(E33<>"", E33>=TODAY(), E33<=TODAY()+3), "Rejoin Follow Up", "") | O33: =IF(AND(G33<>"", G33 > E33, (G33 - E33) <> 1), G33 - E33, "") -> 6
A34: 2632 | B34: =IFERROR(VLOOKUP(A34,'[1]Master File'!$A$2:$C$312,3,0)," ") -> Ratheesh Pv | C34: Annual Leave | D34: 45691 | E34: 45705 | F34: =IF(OR(D34="",E34 =""), "", E34 - D34+ 1) -> 15 | G34: 45706 | I34: =IF(AND(G34="", E34="", D34=""), "", IF(D34>TODAY(), "Applied", IF(G34<>"", IF(G34<E34, "Early Rejoin", "Rejoined"), IF(E34>TODAY(), "On Leave", "Not Rejoined")))) -> Rejoined | N34: =IF(AND(E34<>"", E34>=TODAY(), E34<=TODAY()+3), "Rejoin Follow Up", "") | O34: =IF(AND(G34<>"", G34 > E34, (G34 - E34) <> 1), G34 - E34, "")
A35: 1611 | B35: =IFERROR(VLOOKUP(A35,'[1]Master File'!$A$2:$C$312,3,0)," ") -> Sunil Rana | C35: Annual Leave | D35: 45691 | E35: 45698 | F35: =IF(OR(D35="",E35 =""), "", E35 - D35+ 1) -> 8 | G35: 45699 | I35: =IF(AND(G35="", E35="", D35=""), "", IF(D35>TODAY(), "Applied", IF(G35<>"", IF(G35<E35, "Early Rejoin", "Rejoined"), IF(E35>TODAY(), "On Leave", "Not Rejoined")))) -> Rejoined | N35: =IF(AND(E35<>"", E35>=TODAY(), E35<=TODAY()+3), "Rejoin Follow Up", "") | O35: =IF(AND(G35<>"", G35 > E35, (G35 - E35) <> 1), G35 - E35, "")
A36: 266 | B36: =IFERROR(VLOOKUP(A36,'[1]Master File'!$A$2:$C$312,3,0)," ") -> Shareef Asadullah Muhammad | C36: Annual Leave | D36: 45691 | E36: 45720 | F36: =IF(OR(D36="",E36 =""), "", E36 - D36+ 1) -> 30 | G36: 45715 | I36: =IF(AND(G36="", E36="", D36=""), "", IF(D36>TODAY(), "Applied", IF(G36<>"", IF(G36<E36, "Early Rejoin", "Rejoined"), IF(E36>TODAY(), "On Leave", "Not Rejoined")))) -> Early Rejoin | N36: =IF(AND(E36<>"", E36>=TODAY(), E36<=TODAY()+3), "Rejoin Follow Up", "") | O36: =IF(AND(G36<>"", G36 > E36, (G36 - E36) <> 1), G36 - E36, "")
A37: 1693 | B37: =IFERROR(VLOOKUP(A37,'[1]Master File'!$A$2:$C$312,3,0)," ") -> Shaik Rasheed Ahmed | C37: Emergency Leave | D37: 45691 | E37: 45694 | F37: =IF(OR(D37="",E37 =""), "", E37 - D37+ 1) -> 4 | G37: 45695 | I37: =IF(AND(G37="", E37="", D37=""), "", IF(D37>TODAY(), "Applied", IF(G37<>"", IF(G37<E37, "Early Rejoin", "Rejoined"), IF(E37>TODAY(), "On Leave", "Not Rejoined")))) -> Rejoined | N37: =IF(AND(E37<>"", E37>=TODAY(), E37<=TODAY()+3), "Rejoin Follow Up", "") | O37: =IF(AND(G37<>"", G37 > E37, (G37 - E37) <> 1), G37 - E37, "")
A38: 22 | B38: =IFERROR(VLOOKUP(A38,'[1]Master File'!$A$2:$C$312,3,0)," ") -> Alamgir Hossin Mohammed Sattar | C38: Annual Leave(Medical) | D38: 45693 | E38: 45707 | F38: =IF(OR(D38="",E38 =""), "", E38 - D38+ 1) -> 15 | G38: 45708 | I38: =IF(AND(G38="", E38="", D38=""), "", IF(D38>TODAY(), "Applied", IF(G38<>"", IF(G38<E38, "Early Rejoin", "Rejoined"), IF(E38>TODAY(), "On Leave", "Not Rejoined")))) -> Rejoined | N38: =IF(AND(E38<>"", E38>=TODAY(), E38<=TODAY()+3), "Rejoin Follow Up", "") | O38: =IF(AND(G38<>"", G38 > E38, (G38 - E38) <> 1), G38 - E38, "")
A39: 1399 | B39: =IFERROR(VLOOKUP(A39,'[1]Master File'!$A$2:$C$312,3,0)," ") -> Bachittar Singh | C39: Emergency Leave | D39: 45700 | E39: 45714 | F39: =IF(OR(D39="",E39 =""), "", E39 - D39+ 1) -> 15 | G39: 45729 | I39: =IF(AND(G39="", E39="", D39=""), "", IF(D39>TODAY(), "Applied", IF(G39<>"", IF(G39<E39, "Early Rejoin", "Rejoined"), IF(E39>TODAY(), "On Leave", "Not Rejoined")))) -> Rejoined | N39: =IF(AND(E39<>"", E39>=TODAY(), E39<=TODAY()+3), "Rejoin Follow Up", "") | O39: =IF(AND(G39<>"", G39 > E39, (G39 - E39) <> 1), G39 - E39, "") -> 15
A40: 2738 | B40: Zabiullah Khan | C40: Emergency Leave | D40: 45703 | E40: 45718 | F40: =IF(OR(D40="",E40 =""), "", E40 - D40+ 1) -> 16 | G40: 45719 | I40: =IF(AND(G40="", E40="", D40=""), "", IF(D40>TODAY(), "Applied", IF(G40<>"", IF(G40<E40, "Early Rejoin", "Rejoined"), IF(E40>TODAY(), "On Leave", "Not Rejoined")))) -> Rejoined | N40: =IF(AND(E40<>"", E40>=TODAY(), E40<=TODAY()+3), "Rejoin Follow Up", "") | O40: =IF(AND(G40<>"", G40 > E40, (G40 - E40) <> 1), G40 - E40, "")
A41: 2606 | B41: =IFERROR(VLOOKUP(A41,'[1]Master File'!$A$2:$C$312,3,0)," ") -> Umair Ali Khan | C41: Annual Leave (Umrah) | D41: 45705 | E41: 45718 | F41: =IF(OR(D41="",E41 =""), "", E41 - D41+ 1) -> 14 | G41: 45719 | I41: =IF(AND(G41="", E41="", D41=""), "", IF(D41>TODAY(), "Applied", IF(G41<>"", IF(G41<E41, "Early Rejoin", "Rejoined"), IF(E41>TODAY(), "On Leave", "Not Rejoined")))) -> Rejoined | N41: =IF(AND(E41<>"", E41>=TODAY(), E41<=TODAY()+3), "Rejoin Follow Up", "") | O41: =IF(AND(G41<>"", G41 > E41, (G41 - E41) <> 1), G41 - E41, "")
A42: 2580 | B42: =IFERROR(VLOOKUP(A42,'[1]Master File'!$A$2:$C$312,3,0)," ") -> Nicolo Montesi | C42: Annual leave | D42: 45870 | E42: 45905 | F42: =IF(OR(D42="",E42 =""), "", E42 - D42+ 1) -> 36 | G42: 45906 | I42: =IF(AND(G42="", E42="", D42=""), "", IF(D42>TODAY(), "Applied", IF(G42<>"", IF(G42<E42, "Early Rejoin", "Rejoined"), IF(E42>TODAY(), "On Leave", "Not Rejoined")))) -> Rejoined | N42: =IF(AND(E42<>"", E42>=TODAY(), E42<=TODAY()+3), "Rejoin Follow Up", "") | O42: =IF(AND(G42<>"", G42 > E42, (G42 - E42) <> 1), G42 - E42, "")
A43: 1608 | B43: =IFERROR(VLOOKUP(A43,'[1]Master File'!$A$2:$C$312,3,0)," ") -> Fayaz Ali Mohammed | C43: Emergency Leave | D43: 45705 | E43: 45716 | F43: =IF(OR(D43="",E43 =""), "", E43 - D43+ 1) -> 12 | G43: 29/02/25 | I43: =IF(AND(G43="", E43="", D43=""), "", IF(D43>TODAY(), "Applied", IF(G43<>"", IF(G43<E43, "Early Rejoin", "Rejoined"), IF(E43>TODAY(), "On Leave", "Not Rejoined")))) -> Rejoined | N43: =IF(AND(E43<>"", E43>=TODAY(), E43<=TODAY()+3), "Rejoin Follow Up", "")
A44: 22 | B44: =IFERROR(VLOOKUP(A44,'[1]Master File'!$A$2:$C$312,3,0)," ") -> Alamgir Hossin Mohammed Sattar | C44: Emergency Leave(Medical) | D44: 45707 | E44: 45721 | F44: =IF(OR(D44="",E44 =""), "", E44 - D44+ 1) -> 15 | G44: 45722 | I44: =IF(AND(G44="", E44="", D44=""), "", IF(D44>TODAY(), "Applied", IF(G44<>"", IF(G44<E44, "Early Rejoin", "Rejoined"), IF(E44>TODAY(), "On Leave", "Not Rejoined")))) -> Rejoined | N44: =IF(AND(E44<>"", E44>=TODAY(), E44<=TODAY()+3), "Rejoin Follow Up", "") | O44: =IF(AND(G44<>"", G44 > E44, (G44 - E44) <> 1), G44 - E44, "")
A45: 1282 | B45: =IFERROR(VLOOKUP(A45,'[1]Master File'!$A$2:$C$312,3,0)," ") -> Amrik Suman | C45: Annual Leave | D45: 45712 | E45: 45781 | F45: =IF(OR(D45="",E45 =""), "", E45 - D45+ 1) -> 70 | G45: 45783 | I45: =IF(AND(G45="", E45="", D45=""), "", IF(D45>TODAY(), "Applied", IF(G45<>"", IF(G45<E45, "Early Rejoin", "Rejoined"), IF(E45>TODAY(), "On Leave", "Not Rejoined")))) -> Rejoined | N45: =IF(AND(E45<>"", E45>=TODAY(), E45<=TODAY()+3), "Rejoin Follow Up", "") | O45: =IF(AND(G45<>"", G45 > E45, (G45 - E45) <> 1), G45 - E45, "") -> 2
A46: 356 | B46: =IFERROR(VLOOKUP(A46,'[1]Master File'!$A$2:$C$312,3,0)," ") -> Balwant Singh Munsha Singh | C46: Annual Leave | D46: 45712 | E46: 45770 | F46: =IF(OR(D46="",E46 =""), "", E46 - D46+ 1) -> 59 | G46: 45783 | I46: =IF(AND(G46="", E46="", D46=""), "", IF(D46>TODAY(), "Applied", IF(G46<>"", IF(G46<E46, "Early Rejoin", "Rejoined"), IF(E46>TODAY(), "On Leave", "Not Rejoined")))) -> Rejoined | N46: =IF(AND(E46<>"", E46>=TODAY(), E46<=TODAY()+3), "Rejoin Follow Up", "") | O46: =IF(AND(G46<>"", G46 > E46, (G46 - E46) <> 1), G46 - E46, "") -> 13
A47: 1194 | B47: =IFERROR(VLOOKUP(A47,'[1]Master File'!$A$2:$C$312,3,0)," ") -> Ravi Pal Singh | C47: Annual Leave | D47: 45712 | E47: 45801 | F47: =IF(OR(D47="",E47 =""), "", E47 - D47+ 1) -> 90 | G47: 45853 | I47: =IF(AND(G47="", E47="", D47=""), "", IF(D47>TODAY(), "Applied", IF(G47<>"", IF(G47<E47, "Early Rejoin", "Rejoined"), IF(E47>TODAY(), "On Leave", "Not Rejoined")))) -> Rejoined | N47: =IF(AND(E47<>"", E47>=TODAY(), E47<=TODAY()+3), "Rejoin Follow Up", "") | O47: =IF(AND(G47<>"", G47 > E47, (G47 - E47) <> 1), G47 - E47, "") -> 52
A48: 1376 | B48: =IFERROR(VLOOKUP(A48,'[1]Master File'!$A$2:$C$312,3,0)," ") -> Vishnu Mohanan | C48: Annual Leave | D48: 45718 | E48: 45777 | F48: =IF(OR(D48="",E48 =""), "", E48 - D48+ 1) -> 60 | G48: 45778 | I48: =IF(AND(G48="", E48="", D48=""), "", IF(D48>TODAY(), "Applied", IF(G48<>"", IF(G48<E48, "Early Rejoin", "Rejoined"), IF(E48>TODAY(), "On Leave", "Not Rejoined")))) -> Rejoined | N48: =IF(AND(E48<>"", E48>=TODAY(), E48<=TODAY()+3), "Rejoin Follow Up", "") | O48: =IF(AND(G48<>"", G48 > E48, (G48 - E48) <> 1), G48 - E48, "")
A49: 2702 | B49: =IFERROR(VLOOKUP(A49,'[1]Master File'!$A$2:$C$312,3,0)," ") -> Nitheesh PV | C49: Emergency Leave | D49: 45720 | E49: 45740 | F49: =IF(OR(D49="",E49 =""), "", E49 - D49+ 1) -> 21 | G49: 45741 | I49: =IF(AND(G49="", E49="", D49=""), "", IF(D49>TODAY(), "Applied", IF(G49<>"", IF(G49<E49, "Early Rejoin", "Rejoined"), IF(E49>TODAY(), "On Leave", "Not Rejoined")))) -> Rejoined | N49: =IF(AND(E49<>"", E49>=TODAY(), E49<=TODAY()+3), "Rejoin Follow Up", "") | O49: =IF(AND(G49<>"", G49 > E49, (G49 - E49) <> 1), G49 - E49, "")
A50: 338 | B50: =IFERROR(VLOOKUP(A50,'[1]Master File'!$A$2:$C$312,3,0)," ") -> Jugdayal Sharma Sudeshwar Sharma | C50: Annual Leave | D50: 45726 | E50: 45755 | F50: =IF(OR(D50="",E50 =""), "", E50 - D50+ 1) -> 30 | G50: 45765 | I50: =IF(AND(G50="", E50="", D50=""), "", IF(D50>TODAY(), "Applied", IF(G50<>"", IF(G50<E50, "Early Rejoin", "Rejoined"), IF(E50>TODAY(), "On Leave", "Not Rejoined")))) -> Rejoined | N50: =IF(AND(E50<>"", E50>=TODAY(), E50<=TODAY()+3), "Rejoin Follow Up", "") | O50: =IF(AND(G50<>"", G50 > E50, (G50 - E50) <> 1), G50 - E50, "") -> 10
A51: 2317 | B51: =IFERROR(VLOOKUP(A51,'[1]Master File'!$A$2:$C$312,3,0)," ") -> Adbul Rauf | C51: Emergency Leave | D51: 45734 | E51: 45748 | F51: =IF(OR(D51="",E51 =""), "", E51 - D51+ 1) -> 15 | G51: 45824 | I51: =IF(AND(G51="", E51="", D51=""), "", IF(D51>TODAY(), "Applied", IF(G51<>"", IF(G51<E51, "Early Rejoin", "Rejoined"), IF(E51>TODAY(), "On Leave", "Not Rejoined")))) -> Rejoined | N51: =IF(AND(E51<>"", E51>=TODAY(), E51<=TODAY()+3), "Rejoin Follow Up", "") | O51: =IF(AND(G51<>"", G51 > E51, (G51 - E51) <> 1), G51 - E51, "") -> 76
A52: 2624 | B52: =IFERROR(VLOOKUP(A52,'[1]Master File'!$A$2:$C$312,3,0)," ") -> Ahmad Ullah | C52: Emergency Leave | D52: 45735 | E52: 45746 | F52: =IF(OR(D52="",E52 =""), "", E52 - D52+ 1) -> 12 | G52: 45833 | I52: =IF(AND(G52="", E52="", D52=""), "", IF(D52>TODAY(), "Applied", IF(G52<>"", IF(G52<E52, "Early Rejoin", "Rejoined"), IF(E52>TODAY(), "On Leave", "Not Rejoined")))) -> Rejoined | N52: =IF(AND(E52<>"", E52>=TODAY(), E52<=TODAY()+3), "Rejoin Follow Up", "") | O52: =IF(AND(G52<>"", G52 > E52, (G52 - E52) <> 1), G52 - E52, "") -> 87
A53: 1801 | B53: =IFERROR(VLOOKUP(A53,'[1]Master File'!$A$2:$C$312,3,0)," ") -> Amer Khan Mohammed | C53: Emergency Leave | D53: 45735 | E53: 45750 | F53: =IF(OR(D53="",E53 =""), "", E53 - D53+ 1) -> 16 | G53: 45942 | I53: =IF(AND(G53="", E53="", D53=""), "", IF(D53>TODAY(), "Applied", IF(G53<>"", IF(G53<E53, "Early Rejoin", "Rejoined"), IF(E53>TODAY(), "On Leave", "Not Rejoined")))) -> Rejoined | N53: =IF(AND(E53<>"", E53>=TODAY(), E53<=TODAY()+3), "Rejoin Follow Up", "") | O53: =IF(AND(G53<>"", G53 > E53, (G53 - E53) <> 1), G53 - E53, "") -> 192
A54: 310 | B54: =IFERROR(VLOOKUP(A54,'[1]Master File'!$A$2:$C$312,3,0)," ") -> Vijayalekshmi Neelakanta Pillai Sajeev Kumar | C54: Annual Leave | D54: 45736 | E54: 45797 | F54: =IF(OR(D54="",E54 =""), "", E54 - D54+ 1) -> 62 | G54: 45806 | I54: =IF(AND(G54="", E54="", D54=""), "", IF(D54>TODAY(), "Applied", IF(G54<>"", IF(G54<E54, "Early Rejoin", "Rejoined"), IF(E54>TODAY(), "On Leave", "Not Rejoined")))) -> Rejoined | N54: =IF(AND(E54<>"", E54>=TODAY(), E54<=TODAY()+3), "Rejoin Follow Up", "") | O54: =IF(AND(G54<>"", G54 > E54, (G54 - E54) <> 1), G54 - E54, "") -> 9
A55: 194 | B55: =IFERROR(VLOOKUP(A55,'[1]Master File'!$A$2:$C$312,3,0)," ") -> Olyullah Ali Akbor | C55: Annual Leave | D55: 45736 | E55: 45770 | F55: =IF(OR(D55="",E55 =""), "", E55 - D55+ 1) -> 35 | G55: 45771 | I55: =IF(AND(G55="", E55="", D55=""), "", IF(D55>TODAY(), "Applied", IF(G55<>"", IF(G55<E55, "Early Rejoin", "Rejoined"), IF(E55>TODAY(), "On Leave", "Not Rejoined")))) -> Rejoined | N55: =IF(AND(E55<>"", E55>=TODAY(), E55<=TODAY()+3), "Rejoin Follow Up", "") | O55: =IF(AND(G55<>"", G55 > E55, (G55 - E55) <> 1), G55 - E55, "")
... A61: 801 | B61: =IFERROR(VLOOKUP(A61,'[1]Master File'!$A$2:$C$312,3,0)," ") -> Janeesh Jayakumar Baby | C61: Emergency Leave | D61: 45747 | E61: 45795 | F61: =IF(OR(D61="",E61 =""), "", E61 - D61+ 1) -> 49 | G61: 45796 | I61: =IF(AND(G61="", E61="", D61=""), "", IF(D61>TODAY(), "Applied", IF(G61<>"", IF(G61<E61, "Early Rejoin", "Rejoined"), IF(E61>TODAY(), "On Leave", "Not Rejoined")))) -> Rejoined | N61: =IF(AND(E61<>"", E61>=TODAY(), E61<=TODAY()+3), "Rejoin Follow Up", "") | O61: =IF(AND(G61<>"", G61 > E61, (G61 - E61) <> 1), G61 - E61, "")
A62: 2691 | B62: =IFERROR(VLOOKUP(A62,'[1]Master File'!$A$2:$C$312,3,0)," ") -> Abu thahir | C62: Emergency Leave | D62: 45748 | E62: 45760 | F62: =IF(OR(D62="",E62 =""), "", E62 - D62+ 1) -> 13 | G62: 45761 | I62: =IF(AND(G62="", E62="", D62=""), "", IF(D62>TODAY(), "Applied", IF(G62<>"", IF(G62<E62, "Early Rejoin", "Rejoined"), IF(E62>TODAY(), "On Leave", "Not Rejoined")))) -> Rejoined | N62: =IF(AND(E62<>"", E62>=TODAY(), E62<=TODAY()+3), "Rejoin Follow Up", "")
A63: 2690 | B63: =IFERROR(VLOOKUP(A63,'[1]Master File'!$A$2:$C$312,3,0)," ") -> Joyce V Camposano | C63: Annual Leave | D63: 45748 | E63: 45777 | F63: =IF(OR(D63="",E63 =""), "", E63 - D63+ 1) -> 30 | G63: 31/04/25 | I63: =IF(AND(G63="", E63="", D63=""), "", IF(D63>TODAY(), "Applied", IF(G63<>"", IF(G63<E63, "Early Rejoin", "Rejoined"), IF(E63>TODAY(), "On Leave", "Not Rejoined")))) -> Rejoined | N63: =IF(AND(E63<>"", E63>=TODAY(), E63<=TODAY()+3), "Rejoin Follow Up", "")
A64: 266 | B64: =IFERROR(VLOOKUP(A64,'[1]Master File'!$A$2:$C$312,3,0)," ") -> Shareef Asadullah Muhammad | C64: Annual Leave | D64: 45749 | E64: 45751 | F64: =IF(OR(D64="",E64 =""), "", E64 - D64+ 1) -> 3 | G64: 45754 | I64: =IF(AND(G64="", E64="", D64=""), "", IF(D64>TODAY(), "Applied", IF(G64<>"", IF(G64<E64, "Early Rejoin", "Rejoined"), IF(E64>TODAY(), "On Leave", "Not Rejoined")))) -> Rejoined | N64: =IF(AND(E64<>"", E64>=TODAY(), E64<=TODAY()+3), "Rejoin Follow Up", "") | O64: =IF(AND(G64<>"", G64 > E64, (G64 - E64) <> 1), G64 - E64, "") -> 3
A65: 2078 | B65: =IFERROR(VLOOKUP(A65,'[1]Master File'!$A$2:$C$312,3,0)," ") -> Jabeena Ponmanichi Baboo | C65: Annual Leave | D65: 45750 | E65: 45756 | F65: =IF(OR(D65="",E65 =""), "", E65 - D65+ 1) -> 7 | G65: 45757 | I65: =IF(AND(G65="", E65="", D65=""), "", IF(D65>TODAY(), "Applied", IF(G65<>"", IF(G65<E65, "Early Rejoin", "Rejoined"), IF(E65>TODAY(), "On Leave", "Not Rejoined")))) -> Rejoined | N65: =IF(AND(E65<>"", E65>=TODAY(), E65<=TODAY()+3), "Rejoin Follow Up", "") | O65: =IF(AND(G65<>"", G65 > E65, (G65 - E65) <> 1), G65 - E65, "")
A66: 1417 | B66: =IFERROR(VLOOKUP(A66,'[1]Master File'!$A$2:$C$312,3,0)," ") -> Nawab Afaque Mohammed Khan | C66: Annual Leave | D66: 45750 | E66: 45768 | F66: =IF(OR(D66="",E66 =""), "", E66 - D66+ 1) -> 19 | G66: 45768 | I66: =IF(AND(G66="", E66="", D66=""), "", IF(D66>TODAY(), "Applied", IF(G66<>"", IF(G66<E66, "Early Rejoin", "Rejoined"), IF(E66>TODAY(), "On Leave", "Not Rejoined")))) -> Rejoined | N66: =IF(AND(E66<>"", E66>=TODAY(), E66<=TODAY()+3), "Rejoin Follow Up", "") | O66: =IF(AND(G66<>"", G66 > E66, (G66 - E66) <> 1), G66 - E66, "")
A67: 2397 | B67: =IFERROR(VLOOKUP(A67,'[1]Master File'!$A$2:$C$312,3,0)," ") -> Justin Jose | C67: Emergency Leave | D67: 45751 | E67: 45771 | F67: =IF(OR(D67="",E67 =""), "", E67 - D67+ 1) -> 21 | G67: 45771 | I67: =IF(AND(G67="", E67="", D67=""), "", IF(D67>TODAY(), "Applied", IF(G67<>"", IF(G67<E67, "Early Rejoin", "Rejoined"), IF(E67>TODAY(), "On Leave", "Not Rejoined")))) -> Rejoined | N67: =IF(AND(E67<>"", E67>=TODAY(), E67<=TODAY()+3), "Rejoin Follow Up", "")
A68: 1399 | B68: =IFERROR(VLOOKUP(A68,'[1]Master File'!$A$2:$C$312,3,0)," ") -> Bachittar Singh | C68: Emergency Leave | D68: 45755 | E68: 45761 | F68: =IF(OR(D68="",E68 =""), "", E68 - D68+ 1) -> 7 | G68: 45803 | I68: =IF(AND(G68="", E68="", D68=""), "", IF(D68>TODAY(), "Applied", IF(G68<>"", IF(G68<E68, "Early Rejoin", "Rejoined"), IF(E68>TODAY(), "On Leave", "Not Rejoined")))) -> Rejoined | N68: =IF(AND(E68<>"", E68>=TODAY(), E68<=TODAY()+3), "Rejoin Follow Up", "") | O68: =IF(AND(G68<>"", G68 > E68, (G68 - E68) <> 1), G68 - E68, "") -> 42
A69: 1699 | B69: =IFERROR(VLOOKUP(A69,'[1]Master File'!$A$2:$C$312,3,0)," ") -> Rejanesh Kumar Raghavan | C69: Annual Leave | D69: 45758 | E69: 45818 | F69: =IF(OR(D69="",E69 =""), "", E69 - D69+ 1) -> 61 | G69: 45826 | I69: =IF(AND(G69="", E69="", D69=""), "", IF(D69>TODAY(), "Applied", IF(G69<>"", IF(G69<E69, "Early Rejoin", "Rejoined"), IF(E69>TODAY(), "On Leave", "Not Rejoined")))) -> Rejoined | N69: =IF(AND(E69<>"", E69>=TODAY(), E69<=TODAY()+3), "Rejoin Follow Up", "") | O69: =IF(AND(G69<>"", G69 > E69, (G69 - E69) <> 1), G69 - E69, "") -> 8
A70: 2472 | B70: =IFERROR(VLOOKUP(A70,'[1]Master File'!$A$2:$C$312,3,0)," ") -> Abdur Rehman | C70: Annual Leave | D70: 45759 | E70: 45819 | F70: =IF(OR(D70="",E70 =""), "", E70 - D70+ 1) -> 61 | G70: 45877 | I70: =IF(AND(G70="", E70="", D70=""), "", IF(D70>TODAY(), "Applied", IF(G70<>"", IF(G70<E70, "Early Rejoin", "Rejoined"), IF(E70>TODAY(), "On Leave", "Not Rejoined")))) -> Rejoined | N70: =IF(AND(E70<>"", E70>=TODAY(), E70<=TODAY()+3), "Rejoin Follow Up", "") | O70: =IF(AND(G70<>"", G70 > E70, (G70 - E70) <> 1), G70 - E70, "") -> 58
A71: 279 | B71: =IFERROR(VLOOKUP(A71,'[1]Master File'!$A$2:$C$312,3,0)," ") -> Siful Islam Abdul Samad | C71: Annual Leave | D71: 45760 | E71: 45790 | F71: =IF(OR(D71="",E71 =""), "", E71 - D71+ 1) -> 31 | G71: 45791 | I71: =IF(AND(G71="", E71="", D71=""), "", IF(D71>TODAY(), "Applied", IF(G71<>"", IF(G71<E71, "Early Rejoin", "Rejoined"), IF(E71>TODAY(), "On Leave", "Not Rejoined")))) -> Rejoined | N71: =IF(AND(E71<>"", E71>=TODAY(), E71<=TODAY()+3), "Rejoin Follow Up", "") | O71: =IF(AND(G71<>"", G71 > E71, (G71 - E71) <> 1), G71 - E71, "")
A72: 2595 | B72: =IFERROR(VLOOKUP(A72,'[1]Master File'!$A$2:$C$312,3,0)," ") -> Nand Kishor Mahto | C72: Annual Leave | D72: 45761 | E72: 45820 | F72: =IF(OR(D72="",E72 =""), "", E72 - D72+ 1) -> 60 | G72: 45830 | I72: =IF(AND(G72="", E72="", D72=""), "", IF(D72>TODAY(), "Applied", IF(G72<>"", IF(G72<E72, "Early Rejoin", "Rejoined"), IF(E72>TODAY(), "On Leave", "Not Rejoined")))) -> Rejoined | N72: =IF(AND(E72<>"", E72>=TODAY(), E72<=TODAY()+3), "Rejoin Follow Up", "") | O72: =IF(AND(G72<>"", G72 > E72, (G72 - E72) <> 1), G72 - E72, "") -> 10
A73: 2381 | B73: =IFERROR(VLOOKUP(A73,'[1]Master File'!$A$2:$C$312,3,0)," ") -> Sunil Kumar Kuswaha | C73: Annual Leave | D73: 45761 | E73: 45821 | F73: =IF(OR(D73="",E73 =""), "", E73 - D73+ 1) -> 61 | G73: 45807 | I73: =IF(AND(G73="", E73="", D73=""), "", IF(D73>TODAY(), "Applied", IF(G73<>"", IF(G73<E73, "Early Rejoin", "Rejoined"), IF(E73>TODAY(), "On Leave", "Not Rejoined")))) -> Early Rejoin | N73: =IF(AND(E73<>"", E73>=TODAY(), E73<=TODAY()+3), "Rejoin Follow Up", "") | O73: =IF(AND(G73<>"", G73 > E73, (G73 - E73) <> 1), G73 - E73, "")
A74: 334 | B74: =IFERROR(VLOOKUP(A74,'[1]Master File'!$A$2:$C$312,3,0)," ") -> Zulfikar Ali Abdul Majeed | C74: Annual Leave | D74: 45761 | E74: 45762 | F74: =IF(OR(D74="",E74 =""), "", E74 - D74+ 1) -> 2 | G74: 45763 | I74: =IF(AND(G74="", E74="", D74=""), "", IF(D74>TODAY(), "Applied", IF(G74<>"", IF(G74<E74, "Early Rejoin", "Rejoined"), IF(E74>TODAY(), "On Leave", "Not Rejoined")))) -> Rejoined | N74: =IF(AND(E74<>"", E74>=TODAY(), E74<=TODAY()+3), "Rejoin Follow Up", "") | O74: =IF(AND(G74<>"", G74 > E74, (G74 - E74) <> 1), G74 - E74, "")
A75: 1206 | B75: =IFERROR(VLOOKUP(A75,'[1]Master File'!$A$2:$C$312,3,0)," ") -> Muhammad Saleem Muhammad Asghar | C75: Annual Leave | D75: 45761 | E75: 45820 | F75: =IF(OR(D75="",E75 =""), "", E75 - D75+ 1) -> 60 | G75: 45835 | I75: =IF(AND(G75="", E75="", D75=""), "", IF(D75>TODAY(), "Applied", IF(G75<>"", IF(G75<E75, "Early Rejoin", "Rejoined"), IF(E75>TODAY(), "On Leave", "Not Rejoined")))) -> Rejoined | N75: =IF(AND(E75<>"", E75>=TODAY(), E75<=TODAY()+3), "Rejoin Follow Up", "") | O75: =IF(AND(G75<>"", G75 > E75, (G75 - E75) <> 1), G75 - E75, "") -> 15
A76: 2777 | B76: =IFERROR(VLOOKUP(A76,'[1]Master File'!$A$2:$C$312,3,0)," ") | C76: Emergency Leave | D76: 45761 | E76: 45770 | F76: =IF(OR(D76="",E76 =""), "", E76 - D76+ 1) -> 10 | G76: 45778 | I76: =IF(AND(G76="", E76="", D76=""), "", IF(D76>TODAY(), "Applied", IF(G76<>"", IF(G76<E76, "Early Rejoin", "Rejoined"), IF(E76>TODAY(), "On Leave", "Not Rejoined")))) -> Rejoined | N76: =IF(AND(E76<>"", E76>=TODAY(), E76<=TODAY()+3), "Rejoin Follow Up", "") | O76: =IF(AND(G76<>"", G76 > E76, (G76 - E76) <> 1), G76 - E76, "") -> 8
A77: 835 | B77: =IFERROR(VLOOKUP(A77,'[1]Master File'!$A$2:$C$312,3,0)," ") -> Asim Abbas Sadiq Ali | C77: Paternity Leave | D77: 45764 | E77: 45770 | F77: =IF(OR(D77="",E77 =""), "", E77 - D77+ 1) -> 7 | G77: 45771 | I77: =IF(AND(G77="", E77="", D77=""), "", IF(D77>TODAY(), "Applied", IF(G77<>"", IF(G77<E77, "Early Rejoin", "Rejoined"), IF(E77>TODAY(), "On Leave", "Not Rejoined")))) -> Rejoined | N77: =IF(AND(E77<>"", E77>=TODAY(), E77<=TODAY()+3), "Rejoin Follow Up", "") | O77: =IF(AND(G77<>"", G77 > E77, (G77 - E77) <> 1), G77 - E77, "")
A78: 2580 | B78: =IFERROR(VLOOKUP(A78,'[1]Master File'!$A$2:$C$312,3,0)," ") -> Nicolo Montesi | C78: other, (Easter) | D78: 45765 | E78: 45774 | F78: =IF(OR(D78="",E78 =""), "", E78 - D78+ 1) -> 10 | G78: 45775 | I78: =IF(AND(G78="", E78="", D78=""), "", IF(D78>TODAY(), "Applied", IF(G78<>"", IF(G78<E78, "Early Rejoin", "Rejoined"), IF(E78>TODAY(), "On Leave", "Not Rejoined")))) -> Rejoined | N78: =IF(AND(E78<>"", E78>=TODAY(), E78<=TODAY()+3), "Rejoin Follow Up", "") | O78: =IF(AND(G78<>"", G78 > E78, (G78 - E78) <> 1), G78 - E78, "")
A79: 334 | B79: =IFERROR(VLOOKUP(A79,'[1]Master File'!$A$2:$C$312,3,0)," ") -> Zulfikar Ali Abdul Majeed | C79: Emergency Leave | D79: 45766 | E79: 45770 | F79: =IF(OR(D79="",E79 =""), "", E79 - D79+ 1) -> 5 | G79: 45771 | I79: =IF(AND(G79="", E79="", D79=""), "", IF(D79>TODAY(), "Applied", IF(G79<>"", IF(G79<E79, "Early Rejoin", "Rejoined"), IF(E79>TODAY(), "On Leave", "Not Rejoined")))) -> Rejoined | N79: =IF(AND(E79<>"", E79>=TODAY(), E79<=TODAY()+3), "Rejoin Follow Up", "") | O79: =IF(AND(G79<>"", G79 > E79, (G79 - E79) <> 1), G79 - E79, "")
... A102: 630 | B102: =IFERROR(VLOOKUP(A102,'[1]Master File'!$A$2:$C$312,3,0)," ") -> Amir Hossain Kabir Ahmed | C102: Annual Leave | D102: 45803 | E102: 45862 | F102: =IF(OR(D102="",E102 =""), "", E102 - D102+ 1) -> 60 | G102: 45862 | I102: =IF(AND(G102="", E102="", D102=""), "", IF(D102>TODAY(), "Applied", IF(G102<>"", IF(G102<E102, "Early Rejoin", "Rejoined"), IF(E102>TODAY(), "On Leave", "Not Rejoined")))) -> Rejoined | N102: =IF(AND(E102<>"", E102>=TODAY(), E102<=TODAY()+3), "Rejoin Follow Up", "") | O102: =IF(AND(G102<>"", G102 > E102, (G102 - E102) <> 1), G102 - E102, "")
A103: 2027 | B103: =IFERROR(VLOOKUP(A103,'[1]Master File'!$A$2:$C$312,3,0)," ") -> Rahumathulla Mohamed Naseer | C103: Annual Leave | D103: 45804 | E103: 45834 | F103: 26 | G103: 45828 | I103: =IF(AND(G103="", E103="", D103=""), "", IF(D103>TODAY(), "Applied", IF(G103<>"", IF(G103<E103, "Early Rejoin", "Rejoined"), IF(E103>TODAY(), "On Leave", "Not Rejoined")))) -> Early Rejoin | N103: =IF(AND(E103<>"", E103>=TODAY(), E103<=TODAY()+3), "Rejoin Follow Up", "") | O103: =IF(AND(G103<>"", G103 > E103, (G103 - E103) <> 1), G103 - E103, "")
A104: 1186 | B104: =IFERROR(VLOOKUP(A104,'[1]Master File'!$A$2:$C$312,3,0)," ") -> Israr Ahmed Bashir Ahmed | C104: Annual Leave | D104: 45809 | E104: 45870 | F104: =IF(OR(D104="",E104 =""), "", E104 - D104+ 1) -> 62 | G104: 45872 | I104: =IF(AND(G104="", E104="", D104=""), "", IF(D104>TODAY(), "Applied", IF(G104<>"", IF(G104<E104, "Early Rejoin", "Rejoined"), IF(E104>TODAY(), "On Leave", "Not Rejoined")))) -> Rejoined | N104: =IF(AND(E104<>"", E104>=TODAY(), E104<=TODAY()+3), "Rejoin Follow Up", "") | O104: =IF(AND(G104<>"", G104 > E104, (G104 - E104) <> 1), G104 - E104, "") -> 2
A105: 603 | B105: =IFERROR(VLOOKUP(A105,'[1]Master File'!$A$2:$C$312,3,0)," ") -> Mafijur Matubber Shajahan Fakir | C105: Annual Leave | D105: 45809 | E105: 45874 | F105: =IF(OR(D105="",E105 =""), "", E105 - D105+ 1) -> 66 | G105: 45875 | I105: =IF(AND(G105="", E105="", D105=""), "", IF(D105>TODAY(), "Applied", IF(G105<>"", IF(G105<E105, "Early Rejoin", "Rejoined"), IF(E105>TODAY(), "On Leave", "Not Rejoined")))) -> Rejoined | N105: =IF(AND(E105<>"", E105>=TODAY(), E105<=TODAY()+3), "Rejoin Follow Up", "") | O105: =IF(AND(G105<>"", G105 > E105, (G105 - E105) <> 1), G105 - E105, "")
A106: 2628 | B106: =IFERROR(VLOOKUP(A106,'[1]Master File'!$A$2:$C$312,3,0)," ") -> Sona Kizhakudan Prince | C106: Maternity Leave | D106: 45810 | E106: 45869 | F106: =IF(OR(D106="",E106 =""), "", E106 - D106+ 1) -> 60 | G106: 45870 | I106: =IF(AND(G106="", E106="", D106=""), "", IF(D106>TODAY(), "Applied", IF(G106<>"", IF(G106<E106, "Early Rejoin", "Rejoined"), IF(E106>TODAY(), "On Leave", "Not Rejoined")))) -> Rejoined | N106: =IF(AND(E106<>"", E106>=TODAY(), E106<=TODAY()+3), "Rejoin Follow Up", "") | O106: =IF(AND(G106<>"", G106 > E106, (G106 - E106) <> 1), G106 - E106, "")
A107: 1608 | B107: =IFERROR(VLOOKUP(A107,'[1]Master File'!$A$2:$C$312,3,0)," ") -> Fayaz Ali Mohammed | C107: Annual Leave | D107: 45817 | E107: 45821 | F107: =IF(OR(D107="",E107 =""), "", E107 - D107+ 1) -> 5 | G107: 45822 | I107: =IF(AND(G107="", E107="", D107=""), "", IF(D107>TODAY(), "Applied", IF(G107<>"", IF(G107<E107, "Early Rejoin", "Rejoined"), IF(E107>TODAY(), "On Leave", "Not Rejoined")))) -> Rejoined | N107: =IF(AND(E107<>"", E107>=TODAY(), E107<=TODAY()+3), "Rejoin Follow Up", "") | O107: =IF(AND(G107<>"", G107 > E107, (G107 - E107) <> 1), G107 - E107, "")
A108: 266 | B108: =IFERROR(VLOOKUP(A108,'[1]Master File'!$A$2:$C$312,3,0)," ") -> Shareef Asadullah Muhammad | C108: Annual Leave | D108: 45817 | E108: 45831 | F108: =IF(OR(D108="",E108 =""), "", E108 - D108+ 1) -> 15 | G108: 45834 | I108: =IF(AND(G108="", E108="", D108=""), "", IF(D108>TODAY(), "Applied", IF(G108<>"", IF(G108<E108, "Early Rejoin", "Rejoined"), IF(E108>TODAY(), "On Leave", "Not Rejoined")))) -> Rejoined | N108: =IF(AND(E108<>"", E108>=TODAY(), E108<=TODAY()+3), "Rejoin Follow Up", "") | O108: =IF(AND(G108<>"", G108 > E108, (G108 - E108) <> 1), G108 - E108, "") -> 3
A109: 68 | B109: =IFERROR(VLOOKUP(A109,'[1]Master File'!$A$2:$C$312,3,0)," ") -> Esrafil Patu Ali | C109: Annual Leave | D109: 45817 | E109: 45846 | F109: =IF(OR(D109="",E109 =""), "", E109 - D109+ 1) -> 30 | G109: 45847 | I109: =IF(AND(G109="", E109="", D109=""), "", IF(D109>TODAY(), "Applied", IF(G109<>"", IF(G109<E109, "Early Rejoin", "Rejoined"), IF(E109>TODAY(), "On Leave", "Not Rejoined")))) -> Rejoined | N109: =IF(AND(E109<>"", E109>=TODAY(), E109<=TODAY()+3), "Rejoin Follow Up", "") | O109: =IF(AND(G109<>"", G109 > E109, (G109 - E109) <> 1), G109 - E109, "")
A110: 802 | B110: =IFERROR(VLOOKUP(A110,'[1]Master File'!$A$2:$C$312,3,0)," ") -> Muhammad Pervez Muhammad Idrees | C110: Annual Leave | D110: 45817 | E110: 45876 | F110: =IF(OR(D110="",E110 =""), "", E110 - D110+ 1) -> 60 | G110: 45883 | I110: =IF(AND(G110="", E110="", D110=""), "", IF(D110>TODAY(), "Applied", IF(G110<>"", IF(G110<E110, "Early Rejoin", "Rejoined"), IF(E110>TODAY(), "On Leave", "Not Rejoined")))) -> Rejoined | N110: =IF(AND(E110<>"", E110>=TODAY(), E110<=TODAY()+3), "Rejoin Follow Up", "") | O110: =IF(AND(G110<>"", G110 > E110, (G110 - E110) <> 1), G110 - E110, "") -> 7
A111: 2491 | B111: =IFERROR(VLOOKUP(A111,'[1]Master File'!$A$2:$C$312,3,0)," ") -> Sahib Zada Sher Afzal Khan | C111: Annual Leave | D111: 45817 | E111: 45859 | F111: =IF(OR(D111="",E111 =""), "", E111 - D111+ 1) -> 43 | G111: 45882 | I111: =IF(AND(G111="", E111="", D111=""), "", IF(D111>TODAY(), "Applied", IF(G111<>"", IF(G111<E111, "Early Rejoin", "Rejoined"), IF(E111>TODAY(), "On Leave", "Not Rejoined")))) -> Rejoined | N111: =IF(AND(E111<>"", E111>=TODAY(), E111<=TODAY()+3), "Rejoin Follow Up", "") | O111: =IF(AND(G111<>"", G111 > E111, (G111 - E111) <> 1), G111 - E111, "") -> 23
A112: 2632 | B112: =IFERROR(VLOOKUP(A112,'[1]Master File'!$A$2:$C$312,3,0)," ") -> Ratheesh Pv | C112: Others (Paternity) | D112: 45818 | E112: 45821 | F112: =IF(OR(D112="",E112 =""), "", E112 - D112+ 1) -> 4 | G112: 45822 | I112: =IF(AND(G112="", E112="", D112=""), "", IF(D112>TODAY(), "Applied", IF(G112<>"", IF(G112<E112, "Early Rejoin", "Rejoined"), IF(E112>TODAY(), "On Leave", "Not Rejoined")))) -> Rejoined | N112: =IF(AND(E112<>"", E112>=TODAY(), E112<=TODAY()+3), "Rejoin Follow Up", "") | O112: =IF(AND(G112<>"", G112 > E112, (G112 - E112) <> 1), G112 - E112, "")
A113: 14 | B113: =IFERROR(VLOOKUP(A113,'[1]Master File'!$A$2:$C$312,3,0)," ") -> Afroz Ali Khan Khan | C113: Annual Leave | D113: 45819 | E113: 45823 | F113: =IF(OR(D113="",E113 =""), "", E113 - D113+ 1) -> 5 | G113: 45824 | I113: =IF(AND(G113="", E113="", D113=""), "", IF(D113>TODAY(), "Applied", IF(G113<>"", IF(G113<E113, "Early Rejoin", "Rejoined"), IF(E113>TODAY(), "On Leave", "Not Rejoined")))) -> Rejoined | N113: =IF(AND(E113<>"", E113>=TODAY(), E113<=TODAY()+3), "Rejoin Follow Up", "") | O113: =IF(AND(G113<>"", G113 > E113, (G113 - E113) <> 1), G113 - E113, "")
A114: 2575 | B114: =IFERROR(VLOOKUP(A114,'[1]Master File'!$A$2:$C$312,3,0)," ") -> Ahmed Abdul Latheef Nijar | C114: Annual Leave | D114: 45819 | E114: 45837 | F114: =IF(OR(D114="",E114 =""), "", E114 - D114+ 1) -> 19 | G114: 45838 | I114: =IF(AND(G114="", E114="", D114=""), "", IF(D114>TODAY(), "Applied", IF(G114<>"", IF(G114<E114, "Early Rejoin", "Rejoined"), IF(E114>TODAY(), "On Leave", "Not Rejoined")))) -> Rejoined | N114: =IF(AND(E114<>"", E114>=TODAY(), E114<=TODAY()+3), "Rejoin Follow Up", "") | O114: =IF(AND(G114<>"", G114 > E114, (G114 - E114) <> 1), G114 - E114, "") | P114: Requested from thouseef to extend
A115: 379 | B115: =IFERROR(VLOOKUP(A115,'[1]Master File'!$A$2:$C$312,3,0)," ") -> Mirza Shafiullah Baig | C115: Annual Leave | D115: 45819 | E115: 45848 | F115: =IF(OR(D115="",E115 =""), "", E115 - D115+ 1) -> 30 | G115: 45849 | I115: =IF(AND(G115="", E115="", D115=""), "", IF(D115>TODAY(), "Applied", IF(G115<>"", IF(G115<E115, "Early Rejoin", "Rejoined"), IF(E115>TODAY(), "On Leave", "Not Rejoined")))) -> Rejoined | N115: =IF(AND(E115<>"", E115>=TODAY(), E115<=TODAY()+3), "Rejoin Follow Up", "") | O115: =IF(AND(G115<>"", G115 > E115, (G115 - E115) <> 1), G115 - E115, "")
A116: 2228 | B116: =IFERROR(VLOOKUP(A116,'[1]Master File'!$A$2:$C$312,3,0)," ") -> Mohammad Jawed | C116: Emergency Leave | D116: 45823 | E116: 45838 | F116: =IF(OR(D116="",E116 =""), "", E116 - D116+ 1) -> 16 | G116: 45848 | I116: =IF(AND(G116="", E116="", D116=""), "", IF(D116>TODAY(), "Applied", IF(G116<>"", IF(G116<E116, "Early Rejoin", "Rejoined"), IF(E116>TODAY(), "On Leave", "Not Rejoined")))) -> Rejoined | N116: =IF(AND(E116<>"", E116>=TODAY(), E116<=TODAY()+3), "Rejoin Follow Up", "") | O116: =IF(AND(G116<>"", G116 > E116, (G116 - E116) <> 1), G116 - E116, "") -> 10
A117: 2502 | B117: =IFERROR(VLOOKUP(A117,'[1]Master File'!$A$2:$C$312,3,0)," ") -> Sahadat Sheikh | C117: Annual Leave | D117: 45824 | E117: 45893 | F117: =IF(OR(D117="",E117 =""), "", E117 - D117+ 1) -> 70 | G117: 45897 | I117: =IF(AND(G117="", E117="", D117=""), "", IF(D117>TODAY(), "Applied", IF(G117<>"", IF(G117<E117, "Early Rejoin", "Rejoined"), IF(E117>TODAY(), "On Leave", "Not Rejoined")))) -> Rejoined | N117: =IF(AND(E117<>"", E117>=TODAY(), E117<=TODAY()+3), "Rejoin Follow Up", "") | O117: =IF(AND(G117<>"", G117 > E117, (G117 - E117) <> 1), G117 - E117, "") -> 4
A118: 2638 | B118: =IFERROR(VLOOKUP(A118,'[1]Master File'!$A$2:$C$312,3,0)," ") -> Muhammad Saad Tanveer | C118: Annual Leave | D118: 45831 | E118: 45835 | F118: =IF(OR(D118="",E118 =""), "", E118 - D118+ 1) -> 5 | G118: 45835 | I118: =IF(AND(G118="", E118="", D118=""), "", IF(D118>TODAY(), "Applied", IF(G118<>"", IF(G118<E118, "Early Rejoin", "Rejoined"), IF(E118>TODAY(), "On Leave", "Not Rejoined")))) -> Rejoined | N118: =IF(AND(E118<>"", E118>=TODAY(), E118<=TODAY()+3), "Rejoin Follow Up", "") | O118: =IF(AND(G118<>"", G118 > E118, (G118 - E118) <> 1), G118 - E118, "")
A119: 459 | B119: =IFERROR(VLOOKUP(A119,'[1]Master File'!$A$2:$C$312,3,0)," ") -> Zahangir Alom Abdul Gony | C119: Annual Leave | D119: 45831 | E119: 45892 | F119: =IF(OR(D119="",E119 =""), "", E119 - D119+ 1) -> 62 | G119: 45946 | I119: =IF(AND(G119="", E119="", D119=""), "", IF(D119>TODAY(), "Applied", IF(G119<>"", IF(G119<E119, "Early Rejoin", "Rejoined"), IF(E119>TODAY(), "On Leave", "Not Rejoined")))) -> Rejoined | N119: =IF(AND(E119<>"", E119>=TODAY(), E119<=TODAY()+3), "Rejoin Follow Up", "") | O119: =IF(AND(G119<>"", G119 > E119, (G119 - E119) <> 1), G119 - E119, "") -> 54
A120: 1654 | B120: =IFERROR(VLOOKUP(A120,'[1]Master File'!$A$2:$C$312,3,0)," ") -> Nehal Ahamad Najirullah | C120: Annual Leave | D120: 45836 | E120: 45865 | F120: =IF(OR(D120="",E120 =""), "", E120 - D120+ 1) -> 30 | G120: 45875 | I120: =IF(AND(G120="", E120="", D120=""), "", IF(D120>TODAY(), "Applied", IF(G120<>"", IF(G120<E120, "Early Rejoin", "Rejoined"), IF(E120>TODAY(), "On Leave", "Not Rejoined")))) -> Rejoined | N120: =IF(AND(E120<>"", E120>=TODAY(), E120<=TODAY()+3), "Rejoin Follow Up", "") | O120: =IF(AND(G120<>"", G120 > E120, (G120 - E120) <> 1), G120 - E120, "") -> 10
A121: 600 | B121: =IFERROR(VLOOKUP(A121,'[1]Master File'!$A$2:$C$312,3,0)," ") -> Monir Hossain Nurul Islam Patoari | C121: Annual Leave | D121: 45839 | E121: 45898 | F121: =IF(OR(D121="",E121 =""), "", E121 - D121+ 1) -> 60 | G121: 45902 | I121: =IF(AND(G121="", E121="", D121=""), "", IF(D121>TODAY(), "Applied", IF(G121<>"", IF(G121<E121, "Early Rejoin", "Rejoined"), IF(E121>TODAY(), "On Leave", "Not Rejoined")))) -> Rejoined | N121: =IF(AND(E121<>"", E121>=TODAY(), E121<=TODAY()+3), "Rejoin Follow Up", "") | O121: =IF(AND(G121<>"", G121 > E121, (G121 - E121) <> 1), G121 - E121, "") -> 4
A122: 235 | B122: =IFERROR(VLOOKUP(A122,'[1]Master File'!$A$2:$C$312,3,0)," ") -> Saiyed Anwar Hussain Rizvi | C122: Annual Leave | D122: 45845 | E122: 45863 | F122: =IF(OR(D122="",E122 =""), "", E122 - D122+ 1) -> 19 | G122: 45864 | I122: =IF(AND(G122="", E122="", D122=""), "", IF(D122>TODAY(), "Applied", IF(G122<>"", IF(G122<E122, "Early Rejoin", "Rejoined"), IF(E122>TODAY(), "On Leave", "Not Rejoined")))) -> Rejoined | N122: =IF(AND(E122<>"", E122>=TODAY(), E122<=TODAY()+3), "Rejoin Follow Up", "") | O122: =IF(AND(G122<>"", G122 > E122, (G122 - E122) <> 1), G122 - E122, "")
A123: 1608 | B123: =IFERROR(VLOOKUP(A123,'[1]Master File'!$A$2:$C$312,3,0)," ") -> Fayaz Ali Mohammed | C123: Annual Leave | D123: 45847 | E123: 45854 | F123: =IF(OR(D123="",E123 =""), "", E123 - D123+ 1) -> 8 | G123: 45855 | I123: =IF(AND(G123="", E123="", D123=""), "", IF(D123>TODAY(), "Applied", IF(G123<>"", IF(G123<E123, "Early Rejoin", "Rejoined"), IF(E123>TODAY(), "On Leave", "Not Rejoined")))) -> Rejoined | N123: =IF(AND(E123<>"", E123>=TODAY(), E123<=TODAY()+3), "Rejoin Follow Up", "") | O123: =IF(AND(G123<>"", G123 > E123, (G123 - E123) <> 1), G123 - E123, "")
A124: 2611 | B124: =IFERROR(VLOOKUP(A124,'[1]Master File'!$A$2:$C$312,3,0)," ") -> Sreejesh Kumar | C124: Annual Leave | D124: 45848 | E124: 45877 | F124: =IF(OR(D124="",E124 =""), "", E124 - D124+ 1) -> 30 | G124: 45878 | I124: =IF(AND(G124="", E124="", D124=""), "", IF(D124>TODAY(), "Applied", IF(G124<>"", IF(G124<E124, "Early Rejoin", "Rejoined"), IF(E124>TODAY(), "On Leave", "Not Rejoined")))) -> Rejoined | N124: =IF(AND(E124<>"", E124>=TODAY(), E124<=TODAY()+3), "Rejoin Follow Up", "") | O124: =IF(AND(G124<>"", G124 > E124, (G124 - E124) <> 1), G124 - E124, "")
A125: 2520 | B125: =IFERROR(VLOOKUP(A125,'[1]Master File'!$A$2:$C$312,3,0)," ") -> Salman Qureshi Mohammed | C125: Annual Leave | D125: 45850 | E125: 45880 | F125: =IF(OR(D125="",E125 =""), "", E125 - D125+ 1) -> 31 | G125: 45881 | I125: =IF(AND(G125="", E125="", D125=""), "", IF(D125>TODAY(), "Applied", IF(G125<>"", IF(G125<E125, "Early Rejoin", "Rejoined"), IF(E125>TODAY(), "On Leave", "Not Rejoined")))) -> Rejoined | N125: =IF(AND(E125<>"", E125>=TODAY(), E125<=TODAY()+3), "Rejoin Follow Up", "") | O125: =IF(AND(G125<>"", G125 > E125, (G125 - E125) <> 1), G125 - E125, "")
A126: 1219 | B126: =IFERROR(VLOOKUP(A126,'[1]Master File'!$A$2:$C$312,3,0)," ") -> Azam Qureshi Mohammed | C126: Annual Leave | D126: 45852 | E126: 45881 | F126: =IF(OR(D126="",E126 =""), "", E126 - D126+ 1) -> 30 | G126: 45882 | I126: =IF(AND(G126="", E126="", D126=""), "", IF(D126>TODAY(), "Applied", IF(G126<>"", IF(G126<E126, "Early Rejoin", "Rejoined"), IF(E126>TODAY(), "On Leave", "Not Rejoined")))) -> Rejoined | N126: =IF(AND(E126<>"", E126>=TODAY(), E126<=TODAY()+3), "Rejoin Follow Up", "") | O126: =IF(AND(G126<>"", G126 > E126, (G126 - E126) <> 1), G126 - E126, "")
... A130: 2535 | B130: =IFERROR(VLOOKUP(A130,'[1]Master File'!$A$2:$C$312,3,0)," ") -> Abul Hossain | C130: Annual Leave | D130: 45859 | E130: 45919 | F130: =IF(OR(D130="",E130 =""), "", E130 - D130+ 1) -> 61 | G130: 45920 | I130: =IF(AND(G130="", E130="", D130=""), "", IF(D130>TODAY(), "Applied", IF(G130<>"", IF(G130<E130, "Early Rejoin", "Rejoined"), IF(E130>TODAY(), "On Leave", "Not Rejoined")))) -> Rejoined | N130: =IF(AND(E130<>"", E130>=TODAY(), E130<=TODAY()+3), "Rejoin Follow Up", "") | O130: =IF(AND(G130<>"", G130 > E130, (G130 - E130) <> 1), G130 - E130, "")
...

Sheet Leave report
A1: Employee ID | B1: Name | C1: EML | D1: AL
A2: 2626 | B2: Sanjeev Dubey | C2: 31
A3: 2613 | B3: Amrish Pandey | C3: 31
A4: 2314 | B4: Vinod Sohan | C4: 25 | D4: 6
A5: 2834 | B5: Virendra Singh | C5: 31
A6: 2516 | B6: Rajesh Kumar Choudhary | D6: 31
A7: 2510 | B7: Sanjay Kumar | D7: 31
A8: 2856 | B8: Laxman Armoori | C8: 31
A9: 2707 | B9: Mosim Khan | D9: 28
A10: 2740 | B10: Jagedeesh | C10: 22 | D10: 9
A11: 2594 | B11: Naveed Shams Ur Rehman | C11: 10 | D11: 21 | F11: 46102 | G11: 46122 | H11: =G11-F11+1 -> 21
A12: 976 | B12: Nasar Khan Muhammad Afzal Khan | D12: 29 | F12: 46104 | G12: 46132 | H12: =G12-F12+1 -> 29
A13: 1016 | B13: Mohammed Abul Hasan | D13: 30
A14: 2752 | B14: Madhavkumar | C14: 18
A15: 227 | B15: Rezaul Karim Abdur Rouf | C15: 31
A16: 2478 | B16: Saqib Raza | D16: 22
A17: 2627 | B17: Bheem Kumar Thakur | D17: 31
A18: 2504 | B18: Muhammad Tayyab | D18: 29
A19: 2622 | B19: Ahtsham Khalid | D19: 26
A20: 1076 | B20: Naveed Anjum Muhammad Ramzan Bagoo | D20: 26
A21: 629 | B21: Amir Alam Khan Bahar Karam | D21: 22
A22: 2537 | B22: Rasel Ali Sha | D22: 31
A23: 2014 | B23: Bacha Rashid Fazal Wahid | C23: 10
A24: 2887 | B24: Govindu Ari | C24: 10
A25: 2407 | B25: Radhakrishnan Ramankutty | D25: 4
A26: 1856 | B26: Kumar Gautam Kamal Kishore Prasad | D26: 8
A27: 2845 | B27: Jafar Ali | D27: 1
A28: 1399 | B28: Bachittar Singh | D28: 31
A29: 2777 | B29: Prasantha Kumar | C29: 9 | D29: 18
A30: 338 | B30: Jugdayal Sharma Sudeshwar Sharma | C30: 14 | D30: 11
A31: 979 | B31: Gopakumar Gopinathan Pillai | D31: 11
A32: 2656 | B32: Amith V.R | D32: 17
A33: 1693 | B33: Shaik Rasheed Ahmed | D33: 18 | F33: 46104 | G33: 46121 | H33: =G33-F33+1 -> 18
A34: 1617 | B34: Mohammed Mubeen Mahmood Ali | D34: 4
A35: 2471 | B35: Gobri Yadav | C35: 3
A36: 2798 | B36: SUNNY JAIPAL | C36: 31
A37: 1402 | B37: khushali | C37: 18 | D37: 6
A38: 2636 | B38: SANJOGA THAPA | C38: 14
A39: 1884 | B39: Akhin Varghese | D39: 1
A40: 231 | B40: Rashid Sheikh | D40: 26
A41: 2726 | B41: Md ramjan Mrodha | C41: 11

Sheet Annual Leave Balance
A1: Annual Leave Balance
A2: Employee ID | B2: Name | C2: Designation | D2: Join Date | E2: As On | F2: Total Days | G2: Service Days | H2: EXT Day | I2: EML | J2: Balance on 12/24 | K2: Elgible | L2: Leave Taken | M2: AL Balance | N2: Leave taken in 2025 | O2: Balance | P2: Remarks
A3: 14 | B3: Afroz Ali Khan Khan | C3: Cashier | D3: 39221 | E3: =TODAY() -> 46195 | F3: =E3-D3 -> 6974 | G3: =F3-(H3+I3) -> 6916 | H3: 53 | I3: 5 | J3: 97.5 | K3: =G3/360*30 -> 576.33333 | L3: 434 | M3: =K3-L3 -> 142.33333 | N3: =SUMIFS('Leave Tracker'!F:F,'Leave Tracker'!A:A,'Annual Leave Balance'!A3,'Leave Tracker'!C:C,"Annual Leave") -> 30 | O3: =M3-N3 -> 112.33333
A4: 22 | B4: Alamgir Hossin Mohammed Sattar | C4: Carpenter | D4: 38298 | E4: =TODAY() -> 46195 | F4: =E4-D4 -> 7897 | G4: =F4-(H4+I4) -> 7805 | H4: 92 | I4: 0 | J4: 132.58333 | K4: =G4/360*30 -> 650.41667 | L4: 473 | M4: =K4-L4 -> 177.41667 | N4: =SUMIFS('Leave Tracker'!F:F,'Leave Tracker'!A:A,'Annual Leave Balance'!A4,'Leave Tracker'!C:C,"Annual Leave") -> 61 | O4: =M4-N4 -> 116.41667
A5: 23 | B5: Amanutullah Khan | C5: Aluminium Fabricator | D5: 39277 | E5: =TODAY() -> 46195 | F5: =E5-D5 -> 6918 | G5: =F5-(H5+I5) -> 6740 | H5: 178 | I5: 0 | J5: 173.83333 | K5: =G5/360*30 -> 561.66667 | L5: 343 | M5: =K5-L5 -> 218.66667 | N5: =SUMIFS('Leave Tracker'!F:F,'Leave Tracker'!A:A,'Annual Leave Balance'!A5,'Leave Tracker'!C:C,"Annual Leave") -> 60 | O5: =M5-N5 -> 158.66667
A6: 34 | B6: Ashok Kumar Lekhu Ram | C6: Online QC | D6: 39508 | E6: 46159 | F6: =E6-D6 -> 6651 | G6: =F6-(H6+I6) -> 6240 | H6: 309 | I6: 102 | J6: 3.25 | K6: =G6/360*30 -> 520 | L6: 480 | M6: =K6-L6 -> 40 | N6: =SUMIFS('Leave Tracker'!F:F,'Leave Tracker'!A:A,'Annual Leave Balance'!A6,'Leave Tracker'!C:C,"Annual Leave") -> 33 | O6: =M6-N6 -> 7
A7: 41 | B7: Babuu Ansar Ali | C7: Extruder Operator | D7: 38361 | E7: =TODAY() -> 46195 | F7: =E7-D7 -> 7834 | G7: =F7-(H7+I7) -> 7763 | H7: 71 | I7: 0 | J7: -0.91666667 | K7: =G7/360*30 -> 646.91667 | L7: 580 | M7: =K7-L7 -> 66.916667 | N7: =SUMIFS('Leave Tracker'!F:F,'Leave Tracker'!A:A,'Annual Leave Balance'!A7,'Leave Tracker'!C:C,"Annual Leave") -> 60 | O7: =M7-N7 -> 6.9166667
A8: 67 | B8: Esoj Jose | C8: Electrical Supervisor | D8: 39358 | E8: =TODAY() -> 46195 | F8: =E8-D8 -> 6837 | G8: =F8-(H8+I8) -> 6727 | H8: 52 | I8: 58 | J8: 133.75 | K8: =G8/360*30 -> 560.58333 | L8: 382 | M8: =K8-L8 -> 178.58333 | N8: =SUMIFS('Leave Tracker'!F:F,'Leave Tracker'!A:A,'Annual Leave Balance'!A8,'Leave Tracker'!C:C,"Annual Leave") -> 30 | O8: =M8-N8 -> 148.58333
A9: 68 | B9: Esrafil Patu Ali | C9: Mason | D9: 38980 | E9: =TODAY() -> 46195 | F9: =E9-D9 -> 7215 | G9: =F9-(H9+I9) -> 7214 | H9: 1 | I9: 0 | J9: 227.33333 | K9: =G9/360*30 -> 601.16667 | L9: 329 | M9: =K9-L9 -> 272.16667 | N9: =SUMIFS('Leave Tracker'!F:F,'Leave Tracker'!A:A,'Annual Leave Balance'!A9,'Leave Tracker'!C:C,"Annual Leave") -> 30 | O9: =M9-N9 -> 242.16667
A10: 81 | B10: Gulak Sutradhar Babu Lal | C10: Foreman | D10: 38361 | E10: =TODAY() -> 46195 | F10: =E10-D10 -> 7834 | G10: =F10-(H10+I10) -> 7814 | H10: 20 | I10: 0 | J10: 279.33333 | K10: =G10/360*30 -> 651.16667 | L10: 327 | M10: =K10-L10 -> 324.16667 | N10: =SUMIFS('Leave Tracker'!F:F,'Leave Tracker'!A:A,'Annual Leave Balance'!A10,'Leave Tracker'!C:C,"Annual Leave") -> 0 | O10: =M10-N10 -> 324.16667
A11: 93 | B11: Esmaeil Hassan Rahideh | C11: Group Director – Legal & Communications | D11: 39480 | E11: =TODAY() -> 46195 | F11: =E11-D11 -> 6715 | G11: =F11-(H11+I11) -> 6684 | H11: 31 | I11: 0 | J11: 301.16667 | K11: =G11/360*30 -> 557 | L11: 211 | M11: =K11-L11 -> 346 | N11: =SUMIFS('Leave Tracker'!F:F,'Leave Tracker'!A:A,'Annual Leave Balance'!A11,'Leave Tracker'!C:C,"Annual Leave") -> 0 | O11: 264
A12: 102 | B12: Jayesh Krishnan Gopalakrishnan | C12: Sales Executive | D12: 38964 | E12: =TODAY() -> 46195 | F12: =E12-D12 -> 7231 | G12: =F12-(H12+I12) -> 7207 | H12: 7 | I12: 17 | J12: 105.75 | K12: =G12/360*30 -> 600.58333 | L12: 450 | M12: =K12-L12 -> 150.58333 | N12: =SUMIFS('Leave Tracker'!F:F,'Leave Tracker'!A:A,'Annual Leave Balance'!A12,'Leave Tracker'!C:C,"Annual Leave") -> 29 | O12: =M12-N12 -> 121.58333
A13: 116 | B13: Khorshed Sheikh Nurul Islam | C13: FR Helper Line 3 | D13: 39455 | E13: =TODAY() -> 46195 | F13: =E13-D13 -> 6740 | G13: =F13-(H13+I13) -> 6662 | H13: 78 | I13: 0 | J13: 205.33333 | K13: =G13/360*30 -> 555.16667 | L13: 305 | M13: =K13-L13 -> 250.16667 | N13: =SUMIFS('Leave Tracker'!F:F,'Leave Tracker'!A:A,'Annual Leave Balance'!A13,'Leave Tracker'!C:C,"Annual Leave") -> 0 | O13: =M13-N13 -> 250.16667
A14: 142 | B14: Mary Jaya Francis | C14: Executive Manager – Chairman’s Office | D14: 38936 | E14: =TODAY() -> 46195 | F14: =E14-D14 -> 7259 | G14: =F14-(H14+I14) -> 7259 | H14: 0 | I14: 0 | J14: 239.08333 | K14: =G14/360*30 -> 604.91667 | L14: 321 | M14: =K14-L14 -> 283.91667 | N14: =SUMIFS('Leave Tracker'!F:F,'Leave Tracker'!A:A,'Annual Leave Balance'!A14,'Leave Tracker'!C:C,"Annual Leave") -> 36 | O14: =M14-N14 -> 247.91667 | P14: as on Apr 44
A15: 147 | B15: Md Mosharaf Hossain | C15: Production Supervisor | D15: 39370 | E15: =TODAY() -> 46195 | F15: =E15-D15 -> 6825 | G15: =F15-(H15+I15) -> 6782 | H15: 43 | I15: 0 | J15: 143.33333 | K15: =G15/360*30 -> 565.16667 | L15: 377 | M15: =K15-L15 -> 188.16667 | N15: =SUMIFS('Leave Tracker'!F:F,'Leave Tracker'!A:A,'Annual Leave Balance'!A15,'Leave Tracker'!C:C,"Annual Leave") -> 0 | O15: =M15-N15 -> 188.16667
A16: 166 | B16: Muhammad Inam Noor Muhammad | C16: Chairman Driver | D16: 38976 | E16: 46022 | F16: =E16-D16 -> 7046 | G16: =F16-(H16+I16) -> 6993 | H16: 53 | I16: 0 | J16: 70.333333 | K16: =G16/360*30 -> 582.75 | L16: 482 | M16: =K16-L16 -> 100.75 | N16: =SUMIFS('Leave Tracker'!F:F,'Leave Tracker'!A:A,'Annual Leave Balance'!A16,'Leave Tracker'!C:C,"Annual Leave") -> 62 | O16: =M16-N16 -> 38.75
A17: 190 | B17: Nasir Aziz Masih Aziz | C17: Sales Executive / Cricketer | D17: 38969 | E17: =TODAY() -> 46195 | F17: =E17-D17 -> 7226 | G17: =F17-(H17+I17) -> 7196 | H17: 6 | I17: 24 | J17: 206.83333 | K17: =G17/360*30 -> 599.66667 | L17: 348 | M17: =K17-L17 -> 251.66667 | N17: =SUMIFS('Leave Tracker'!F:F,'Leave Tracker'!A:A,'Annual Leave Balance'!A17,'Leave Tracker'!C:C,"Annual Leave") -> 9 | O17: =M17-N17 -> 242.66667
A18: 194 | B18: Olyullah Ali Akbor | C18: Supervisor | D18: 38620 | E18: =TODAY() -> 46195 | F18: =E18-D18 -> 7575 | G18: =F18-(H18+I18) -> 7434 | H18: 141 | I18: 0 | J18: 242.66667 | K18: =G18/360*30 -> 619.5 | L18: 332 | M18: =K18-L18 -> 287.5 | N18: =SUMIFS('Leave Tracker'!F:F,'Leave Tracker'!A:A,'Annual Leave Balance'!A18,'Leave Tracker'!C:C,"Annual Leave") -> 35 | O18: =M18-N18 -> 252.5
A19: 225 | B19: Ravikumar Velayudhan Velayudhan | C19: Production Supervisor | D19: 39452 | E19: =TODAY() -> 46195 | F19: =E19-D19 -> 6743 | G19: =F19-(H19+I19) -> 6724 | H19: 19 | I19: 0 | J19: 91.5 | K19: =G19/360*30 -> 560.33333 | L19: 424 | M19: =K19-L19 -> 136.33333 | N19: =SUMIFS('Leave Tracker'!F:F,'Leave Tracker'!A:A,'Annual Leave Balance'!A19,'Leave Tracker'!C:C,"Annual Leave") -> 0 | O19: =M19-N19 -> 136.33333
A20: 227 | B20: Rezaul Karim Abdur Rouf | C20: Extruder Operator | D20: 39365 | E20: =TODAY() -> 46195 | F20: =E20-D20 -> 6830 | G20: =F20-(H20+I20) -> 6511 | H20: 289 | I20: 30 | J20: 10.75 | K20: =G20/360*30 -> 542.58333 | L20: 487 | M20: =K20-L20 -> 55.583333 | N20: =SUMIFS('Leave Tracker'!F:F,'Leave Tracker'!A:A,'Annual Leave Balance'!A20,'Leave Tracker'!C:C,"Annual Leave") -> 0 | O20: =M20-N20 -> 55.583333
A21: 231 | B21: Roshid Sheikh Taleb Ali Sheikh | C21: Helper | D21: 38980 | E21: =TODAY() -> 46195 | F21: =E21-D21 -> 7215 | G21: =F21-(H21+I21) -> 7117 | H21: 98 | I21: 0 | J21: 134.25 | K21: =G21/360*30 -> 593.08333 | L21: 414 | M21: =K21-L21 -> 179.08333 | N21: =SUMIFS('Leave Tracker'!F:F,'Leave Tracker'!A:A,'Annual Leave Balance'!A21,'Leave Tracker'!C:C,"Annual Leave") -> 0 | O21: =M21-N21 -> 179.08333
A22: 232 | B22: Ruhul Amin Haian Saiyal | C22: End Cutting Operator | D22: 39442 | E22: =TODAY() -> 46195 | F22: =E22-D22 -> 6753 | G22: =F22-(H22+I22) -> 6664 | H22: 89 | I22: 0 | J22: 74.5 | K22: =G22/360*30 -> 555.33333 | L22: 436 | M22: =K22-L22 -> 119.33333 | N22: =SUMIFS('Leave Tracker'!F:F,'Leave Tracker'!A:A,'Annual Leave Balance'!A22,'Leave Tracker'!C:C,"Annual Leave") -> 60 | O22: =M22-N22 -> 59.333333
A23: 234 | B23: Saidur Abdul Samad | C23: Lamination Operator | D23: 38388 | E23: =TODAY() -> 46195 | F23: =E23-D23 -> 7807 | G23: =F23-(H23+I23) -> 7427 | H23: 349 | I23: 31 | J23: 107.08333 | K23: =G23/360*30 -> 618.91667 | L23: 467 | M23: =K23-L23 -> 151.91667 | N23: =SUMIFS('Leave Tracker'!F:F,'Leave Tracker'!A:A,'Annual Leave Balance'!A23,'Leave Tracker'!C:C,"Annual Leave") -> 61 | O23: =M23-N23 -> 90.916667
A24: 235 | B24: Saiyed Anwar Hussain Rizvi | C24: Senior Manager | D24: 38808 | E24: =TODAY() -> 46195 | F24: =E24-D24 -> 7387 | G24: =F24-(H24+I24) -> 7399 | H24: -12 | I24: 0 | J24: 225.75 | K24: =G24/360*30 -> 616.58333 | L24: 346 | M24: =K24-L24 -> 270.58333 | N24: =SUMIFS('Leave Tracker'!F:F,'Leave Tracker'!A:A,'Annual Leave Balance'!A24,'Leave Tracker'!C:C,"Annual Leave") -> 27 | O24: =M24-N24 -> 243.58333
A25: 266 | B25: Shareef Asadullah Muhammad | C25: PR Manager | D25: 39337 | E25: =TODAY() -> 46195 | F25: =E25-D25 -> 6858 | G25: =F25-(H25+I25) -> 6797 | H25: 61 | I25: 0 | J25: 105.58333 | K25: =G25/360*30 -> 566.41667 | L25: 416 | M25: =K25-L25 -> 150.41667 | N25: =SUMIFS('Leave Tracker'!F:F,'Leave Tracker'!A:A,'Annual Leave Balance'!A25,'Leave Tracker'!C:C,"Annual Leave") -> 48 | O25: =M25-N25 -> 102.41667
A26: 276 | B26: Shoukath Ahmed Khan | C26: Security Guard | D26: 39062 | E26: =TODAY() -> 46195 | F26: =E26-D26 -> 7133 | G26: =F26-(H26+I26) -> 6937 | H26: 196 | I26: 0 | J26: 108.25 | K26: =G26/360*30 -> 578.08333 | L26: 425 | M26: =K26-L26 -> 153.08333 | N26: =SUMIFS('Leave Tracker'!F:F,'Leave Tracker'!A:A,'Annual Leave Balance'!A26,'Leave Tracker'!C:C,"Annual Leave") -> 0 | O26: =M26-N26 -> 153.08333
A27: 279 | B27: Siful Islam Abdul Samad | C27: Production Supervisor | D27: 38682 | E27: =TODAY() -> 46195 | F27: =E27-D27 -> 7513 | G27: =F27-(H27+I27) -> 7376 | H27: 90 | I27: 47 | J27: -18.166667 | K27: =G27/360*30 -> 614.66667 | L27: 588 | M27: =K27-L27 -> 26.666667 | N27: =SUMIFS('Leave Tracker'!F:F,'Leave Tracker'!A:A,'Annual Leave Balance'!A27,'Leave Tracker'!C:C,"Annual Leave") -> 111 | O27: =M27-N27 -> -84.333333
A28: 310 | B28: Vijayalekshmi Neelakanta Pillai Sajeev Kumar | C28: Temporary Forklift Operator | D28: 39061 | E28: =TODAY() -> 46195 | F28: =E28-D28 -> 7134 | G28: =F28-(H28+I28) -> 6887 | H28: 247 | I28: 0 | J28: -12.916667 | K28: =G28/360*30 -> 573.91667 | L28: 542 | M28: =K28-L28 -> 31.916667 | N28: =SUMIFS('Leave Tracker'!F:F,'Leave Tracker'!A:A,'Annual Leave Balance'!A28,'Leave Tracker'!C:C,"Annual Leave") -> 62 | O28: =M28-N28 -> -30.083333
... A31: 334 | B31: Zulfikar Ali Abdul Majeed | C31: Regional Manager | D31: 38476 | E31: =TODAY() -> 46195 | F31: =E31-D31 -> 7719 | G31: =F31-(H31+I31) -> 7656 | H31: 63 | I31: 0 | J31: 262.16667 | K31: =G31/360*30 -> 638 | L31: 331 | M31: =K31-L31 -> 307 | N31: =SUMIFS('Leave Tracker'!F:F,'Leave Tracker'!A:A,'Annual Leave Balance'!A31,'Leave Tracker'!C:C,"Annual Leave") -> 13 | O31: =M31-N31 -> 294
A32: 338 | B32: Jugdayal Sharma Sudeshwar Sharma | C32: Foreman | D32: 42747 | E32: =TODAY() -> 46195 | F32: =E32-D32 -> 3448 | G32: =F32-(H32+I32) -> 3276 | H32: 172 | I32: 0 | J32: 25.166667 | K32: =G32/360*30 -> 273 | L32: 203 | M32: =K32-L32 -> 70 | N32: 62 | O32: =M32-N32 -> 8
A33: 351 | B33: Shameem Hossain Mofser Mollah | C33: Supervisor | D33: 39547 | E33: =TODAY() -> 46195 | F33: =E33-D33 -> 6648 | G33: =F33-(H33+I33) -> 6645 | H33: 3 | I33: 0 | J33: 91.916667 | K33: =G33/360*30 -> 553.75 | L33: 417 | M33: =K33-L33 -> 136.75 | N33: =SUMIFS('Leave Tracker'!F:F,'Leave Tracker'!A:A,'Annual Leave Balance'!A33,'Leave Tracker'!C:C,"Annual Leave") -> 63 | O33: =M33-N33 -> 73.75
A34: 356 | B34: Balwant Singh Munsha Singh | C34: Helper | D34: 39568 | E34: =TODAY() -> 46195 | F34: =E34-D34 -> 6627 | G34: =F34-(H34+I34) -> 6518 | H34: 94 | I34: 15 | J34: 199.33333 | K34: =G34/360*30 -> 543.16667 | L34: 299 | M34: =K34-L34 -> 244.16667 | N34: =SUMIFS('Leave Tracker'!F:F,'Leave Tracker'!A:A,'Annual Leave Balance'!A34,'Leave Tracker'!C:C,"Annual Leave") -> 59 | O34: =M34-N34 -> 185.16667
A35: 360 | B35: Moazam Qureshi Mohammed | C35: Asst. Operation Manager | D35: 39578 | E35: =TODAY() -> 46195 | F35: =E35-D35 -> 6617 | G35: =F35-(H35+I35) -> 6605 | H35: 12 | I35: 0 | J35: 185.58333 | K35: =G35/360*30 -> 550.41667 | L35: 320 | M35: =K35-L35 -> 230.41667 | N35: =SUMIFS('Leave Tracker'!F:F,'Leave Tracker'!A:A,'Annual Leave Balance'!A35,'Leave Tracker'!C:C,"Annual Leave") -> 20 | O35: =M35-N35 -> 210.41667
A36: 363 | B36: Badri Bahadur Budhathoki | C36: Security Guard | D36: 39576 | E36: =TODAY() -> 46195 | F36: =E36-D36 -> 6619 | G36: =F36-(H36+I36) -> 6539 | H36: 64 | I36: 16 | J36: 169.08333 | K36: =G36/360*30 -> 544.91667 | L36: 331 | M36: =K36-L36 -> 213.91667 | N36: =SUMIFS('Leave Tracker'!F:F,'Leave Tracker'!A:A,'Annual Leave Balance'!A36,'Leave Tracker'!C:C,"Annual Leave") -> 0 | O36: =M36-N36 -> 213.91667
A37: 367 | B37: Ratan Sheikh Nurul Islam | C37: House Keeper | D37: 39599 | E37: =TODAY() -> 46195 | F37: =E37-D37 -> 6596 | G37: =F37-(H37+I37) -> 6480 | H37: 86 | I37: 30 | J37: 122.16667 | K37: =G37/360*30 -> 540 | L37: 373 | M37: =K37-L37 -> 167 | N37: =SUMIFS('Leave Tracker'!F:F,'Leave Tracker'!A:A,'Annual Leave Balance'!A37,'Leave Tracker'!C:C,"Annual Leave") -> 0 | O37: =M37-N37 -> 167
A38: 379 | B38: Mirza Shafiullah Baig | C38: Purchase Assistant | D38: 39641 | E38: =TODAY() -> 46195 | F38: =E38-D38 -> 6554 | G38: =F38-(H38+I38) -> 6156 | H38: 398 | I38: 0 | J38: 136.16667 | K38: =G38/360*30 -> 513 | L38: 332 | M38: =K38-L38 -> 181 | N38: =SUMIFS('Leave Tracker'!F:F,'Leave Tracker'!A:A,'Annual Leave Balance'!A38,'Leave Tracker'!C:C,"Annual Leave") -> 30 | O38: =M38-N38 -> 151
A39: 389 | B39: Mehedi Hasan Abdul Aziz | C39: Office Boy | D39: 39654 | E39: =TODAY() -> 46195 | F39: =E39-D39 -> 6541 | G39: =F39-(H39+I39) -> 6410 | H39: 131 | I39: 0 | J39: 55.333333 | K39: =G39/360*30 -> 534.16667 | L39: 434 | M39: =K39-L39 -> 100.16667 | N39: =SUMIFS('Leave Tracker'!F:F,'Leave Tracker'!A:A,'Annual Leave Balance'!A39,'Leave Tracker'!C:C,"Annual Leave") -> 0 | O39: =M39-N39 -> 100.16667
A40: 394 | B40: Kamal Hossain Tofazzal Mollah | C40: House Keeper | D40: 39649 | E40: =TODAY() -> 46195 | F40: =E40-D40 -> 6546 | G40: =F40-(H40+I40) -> 6348 | H40: 168 | I40: 30 | J40: 123.16667 | K40: =G40/360*30 -> 529 | L40: 361 | M40: =K40-L40 -> 168 | N40: =SUMIFS('Leave Tracker'!F:F,'Leave Tracker'!A:A,'Annual Leave Balance'!A40,'Leave Tracker'!C:C,"Annual Leave") -> 62 | O40: =M40-N40 -> 106
A41: 399 | B41: Mohammed Parvez Kamal Uddin | C41: End Cutting Operator | D41: 39659 | E41: =TODAY() -> 46195 | F41: =E41-D41 -> 6536 | G41: =F41-(H41+I41) -> 6403 | H41: 115 | I41: 18 | J41: 187.75 | K41: =G41/360*30 -> 533.58333 | L41: 301 | M41: =K41-L41 -> 232.58333 | N41: =SUMIFS('Leave Tracker'!F:F,'Leave Tracker'!A:A,'Annual Leave Balance'!A41,'Leave Tracker'!C:C,"Annual Leave") -> 67 | O41: =M41-N41 -> 165.58333
A42: 434 | B42: Liton Zamal Hossain | C42: Lamination Operator | D42: 39742 | E42: =TODAY() -> 46195 | F42: =E42-D42 -> 6453 | G42: =F42-(H42+I42) -> 6439 | H42: 14 | I42: 0 | J42: 100.75 | K42: =G42/360*30 -> 536.58333 | L42: 391 | M42: =K42-L42 -> 145.58333 | N42: =SUMIFS('Leave Tracker'!F:F,'Leave Tracker'!A:A,'Annual Leave Balance'!A42,'Leave Tracker'!C:C,"Annual Leave") -> 0 | O42: =M42-N42 -> 145.58333
A43: 439 | B43: Prasith Ponnara Kandy | C43: Assistant Manager | D43: 39746 | E43: =TODAY() -> 46195 | F43: =E43-D43 -> 6449 | G43: =F43-(H43+I43) -> 6381 | H43: 10 | I43: 58 | J43: 143.91667 | K43: =G43/360*30 -> 531.75 | L43: 343 | M43: =K43-L43 -> 188.75 | N43: =SUMIFS('Leave Tracker'!F:F,'Leave Tracker'!A:A,'Annual Leave Balance'!A43,'Leave Tracker'!C:C,"Annual Leave") -> 15 | O43: =M43-N43 -> 173.75
A44: 453 | B44: Saadullah Khan Nawab Dawood Khan | C44: Director- Operational & Sales Support | D44: 44378 | E44: =TODAY() -> 46195 | F44: =E44-D44 -> 1817 | G44: =F44-(H44+I44) -> 1819 | H44: -2 | I44: 0 | J44: -53.25 | K44: =G44/360*30 -> 151.58333 | L44: 160 | M44: =K44-L44 -> -8.4166667 | N44: =SUMIFS('Leave Tracker'!F:F,'Leave Tracker'!A:A,'Annual Leave Balance'!A44,'Leave Tracker'!C:C,"Annual Leave") -> 0 | O44: =M44-N44 -> -8.4166667
... A55: 603 | B55: Mafijur Matubber Shajahan Fakir | C55: Production Supervisor | D55: 40140 | E55: =TODAY() -> 46195 | F55: =E55-D55 -> 6055 | G55: =F55-(H55+I55) -> 5854 | H55: 201 | I55: 0 | J55: 140 | K55: =G55/360*30 -> 487.83333 | L55: 303 | M55: =K55-L55 -> 184.83333 | N55: =SUMIFS('Leave Tracker'!F:F,'Leave Tracker'!A:A,'Annual Leave Balance'!A55,'Leave Tracker'!C:C,"Annual Leave") -> 66 | O55: =M55-N55 -> 118.83333
A56: 629 | B56: Amir Alam Khan Bahar Karam | C56: Trailer Driver - 68503 | D56: 40223 | E56: 46022 | F56: =E56-D56 -> 5799 | G56: =F56-(H56+I56) -> 5677 | H56: 108 | I56: 14 | J56: 40.666667 | K56: =G56/360*30 -> 473.08333 | L56: 402 | M56: =K56-L56 -> 71.083333 | N56: =SUMIFS('Leave Tracker'!F:F,'Leave Tracker'!A:A,'Annual Leave Balance'!A56,'Leave Tracker'!C:C,"Annual Leave") -> 0 | O56: =M56-N56 -> 71.083333
A57: 630 | B57: Amir Hossain Kabir Ahmed | C57: Imam | D57: 40171 | E57: =TODAY() -> 46195 | F57: =E57-D57 -> 6024 | G57: =F57-(H57+I57) -> 6021 | H57: 3 | I57: 0 | J57: 89.916667 | K57: =G57/360*30 -> 501.75 | L57: 367 | M57: =K57-L57 -> 134.75 | N57: =SUMIFS('Leave Tracker'!F:F,'Leave Tracker'!A:A,'Annual Leave Balance'!A57,'Leave Tracker'!C:C,"Annual Leave") -> 60 | O57: =M57-N57 -> 74.75
A58: 659 | B58: Monir Hossain Reno Miah | C58: FR Igglo Helper Line 1 | D58: 40398 | E58: =TODAY() -> 46195 | F58: =E58-D58 -> 5797 | G58: =F58-(H58+I58) -> 5663 | H58: 134 | I58: 0 | J58: 125.08333 | K58: =G58/360*30 -> 471.91667 | L58: 302 | M58: =K58-L58 -> 169.91667 | N58: =SUMIFS('Leave Tracker'!F:F,'Leave Tracker'!A:A,'Annual Leave Balance'!A58,'Leave Tracker'!C:C,"Annual Leave") -> 60 | O58: =M58-N58 -> 109.91667
A59: 670 | B59: Mohammad Masum Harunur Rashid | C59: Coating Operator | D59: 40408 | E59: =TODAY() -> 46195 | F59: =E59-D59 -> 5787 | G59: =F59-(H59+I59) -> 5411 | H59: 376 | I59: 0 | J59: 160.08333 | K59: =G59/360*30 -> 450.91667 | L59: 246 | M59: =K59-L59 -> 204.91667 | N59: =SUMIFS('Leave Tracker'!F:F,'Leave Tracker'!A:A,'Annual Leave Balance'!A59,'Leave Tracker'!C:C,"Annual Leave") -> 0 | O59: =M59-N59 -> 204.91667
A60: 791 | B60: Yuvaraj Chauhan | C60: Office Boy | D60: 40675 | E60: =TODAY() -> 46195 | F60: =E60-D60 -> 5520 | G60: =F60-(H60+I60) -> 5471 | H60: 42 | I60: 7 | J60: 12.083333 | K60: =G60/360*30 -> 455.91667 | L60: 399 | M60: =K60-L60 -> 56.916667 | N60: =SUMIFS('Leave Tracker'!F:F,'Leave Tracker'!A:A,'Annual Leave Balance'!A60,'Leave Tracker'!C:C,"Annual Leave") -> 0 | O60: =M60-N60 -> 56.916667
A61: 801 | B61: Janeesh Jayakumar Baby | C61: Trailer Driver / 3 Tonne Pick Up 62755 | D61: 40664 | E61: 46022 | F61: =E61-D61 -> 5358 | G61: =F61-(H61+I61) -> 5139 | H61: 198 | I61: 21 | J61: -15.166667 | K61: =G61/360*30 -> 428.25 | L61: 413 | M61: =K61-L61 -> 15.25 | N61: =SUMIFS('Leave Tracker'!F:F,'Leave Tracker'!A:A,'Annual Leave Balance'!A61,'Leave Tracker'!C:C,"Annual Leave") -> 0 | O61: =M61-N61 -> 15.25
A62: 802 | B62: Muhammad Pervez Muhammad Idrees | C62: Sr.Maintenance Helper | D62: 40642 | E62: =TODAY() -> 46195 | F62: =E62-D62 -> 5553 | G62: =F62-(H62+I62) -> 5426 | H62: 93 | I62: 34 | J62: 32.333333 | K62: =G62/360*30 -> 452.16667 | L62: 375 | M62: =K62-L62 -> 77.166667 | N62: =SUMIFS('Leave Tracker'!F:F,'Leave Tracker'!A:A,'Annual Leave Balance'!A62,'Leave Tracker'!C:C,"Annual Leave") -> 60 | O62: =M62-N62 -> 17.166667
A63: 835 | B63: Asim Abbas Sadiq Ali | C63: Credit Controller | D63: 40696 | E63: =TODAY() -> 46195 | F63: =E63-D63 -> 5499 | G63: =F63-(H63+I63) -> 5497 | H63: 2 | I63: 0 | J63: 139.25 | K63: =G63/360*30 -> 458.08333 | L63: 274 | M63: =K63-L63 -> 184.08333 | N63: =SUMIFS('Leave Tracker'!F:F,'Leave Tracker'!A:A,'Annual Leave Balance'!A63,'Leave Tracker'!C:C,"Annual Leave") -> 37 | O63: =M63-N63 -> 147.08333
A64: 924 | B64: Chandrakant Bhaskarbhai Pawar | C64: Group CFO | D64: 41023 | E64: =TODAY() -> 46195 | F64: =E64-D64 -> 5172 | G64: =F64-(H64+I64) -> 4994 | H64: 175 | I64: 3 | J64: 66.333333 | K64: =G64/360*30 -> 416.16667 | L64: 305 | M64: =K64-L64 -> 111.16667 | N64: =SUMIFS('Leave Tracker'!F:F,'Leave Tracker'!A:A,'Annual Leave Balance'!A64,'Leave Tracker'!C:C,"Annual Leave") -> 3 | O64: =M64-N64 -> 108.16667
A65: 945 | B65: Muhammad Irfan Ramzan | C65: Helper | D65: 41205 | E65: =TODAY() -> 46195 | F65: =E65-D65 -> 4990 | G65: =F65-(H65+I65) -> 4905 | H65: 70 | I65: 15 | J65: 61.916667 | K65: =G65/360*30 -> 408.75 | L65: 302 | M65: =K65-L65 -> 106.75 | N65: =SUMIFS('Leave Tracker'!F:F,'Leave Tracker'!A:A,'Annual Leave Balance'!A65,'Leave Tracker'!C:C,"Annual Leave") -> 60 | O65: =M65-N65 -> 46.75
A66: 951 | B66: Biju Sasidharan Susheela | C66: End Cutting Operator | D66: 41248 | E66: =TODAY() -> 46195 | F66: =E66-D66 -> 4947 | G66: =F66-(H66+I66) -> 4834 | H66: 113 | I66: 0 | J66: -13 | K66: =G66/360*30 -> 402.83333 | L66: 371 | M66: =K66-L66 -> 31.833333 | N66: =SUMIFS('Leave Tracker'!F:F,'Leave Tracker'!A:A,'Annual Leave Balance'!A66,'Leave Tracker'!C:C,"Annual Leave") -> 60 | O66: =M66-N66 -> -28.166667
A67: 976 | B67: Nasar Khan Muhammad Afzal Khan | C67: Bus & Light Vehicle Driver - Nissan 14 Seater | D67: 41276 | E67: 46022 | F67: =E67-D67 -> 4746 | G67: =F67-(H67+I67) -> 4622 | H67: 109 | I67: 15 | J67: 37.75 | K67: =G67/360*30 -> 385.16667 | L67: 317 | M67: =K67-L67 -> 68.166667 | N67: =SUMIFS('Leave Tracker'!F:F,'Leave Tracker'!A:A,'Annual Leave Balance'!A67,'Leave Tracker'!C:C,"Annual Leave") -> 39 | O67: =M67-N67 -> 29.166667
A68: 979 | B68: Gopakumar Gopinathan Pillai | C68: Asst Manager Planning | D68: 41296 | E68: =TODAY() -> 46195 | F68: =E68-D68 -> 4899 | G68: =F68-(H68+I68) -> 4822 | H68: 77 | I68: 0 | J68: -6 | K68: =G68/360*30 -> 401.83333 | L68: 363 | M68: =K68-L68 -> 38.833333 | N68: =SUMIFS('Leave Tracker'!F:F,'Leave Tracker'!A:A,'Annual Leave Balance'!A68,'Leave Tracker'!C:C,"Annual Leave") -> 16 | O68: =M68-N68 -> 22.833333
A69: 999 | B69: Gul Meen Khan Lal Meer Khan | C69: Driver - Toyota Avanza | D69: 41365 | E69: 46022 | F69: =E69-D69 -> 4657 | G69: =F69-(H69+I69) -> 4561 | H69: 96 | I69: 0 | J69: 35.666667 | K69: =G69/360*30 -> 380.08333 | L69: 314 | M69: =K69-L69 -> 66.083333 | N69: =SUMIFS('Leave Tracker'!F:F,'Leave Tracker'!A:A,'Annual Leave Balance'!A69,'Leave Tracker'!C:C,"Annual Leave") -> 60 | O69: =M69-N69 -> 6.0833333
A70: 1016 | B70: Mohammed Abul Hasan | C70: Supervisor | D70: 41410 | E70: =TODAY() -> 46195 | F70: =E70-D70 -> 4785 | G70: =F70-(H70+I70) -> 4767 | H70: 18 | I70: 0 | J70: 142.41667 | K70: =G70/360*30 -> 397.25 | L70: 210 | M70: =K70-L70 -> 187.25 | N70: 60 | O70: =M70-N70 -> 127.25
A71: 1076 | B71: Naveed Anjum Muhammad Ramzan Bagoo | C71: Electrician | D71: 40717 | E71: =TODAY() -> 46195 | F71: =E71-D71 -> 5478 | G71: =F71-(H71+I71) -> 5440 | H71: 17 | I71: 21 | J71: 18.5 | K71: =G71/360*30 -> 453.33333 | L71: 390 | M71: =K71-L71 -> 63.333333 | N71: =SUMIFS('Leave Tracker'!F:F,'Leave Tracker'!A:A,'Annual Leave Balance'!A71,'Leave Tracker'!C:C,"Annual Leave") -> 0 | O71: =M71-N71 -> 63.333333
A72: 1077 | B72: Razib Shahid Miah | C72: Maintenance Fitter | D72: 38980 | E72: =TODAY() -> 46195 | F72: =E72-D72 -> 7215 | G72: =F72-(H72+I72) -> 6979 | H72: 236 | I72: 0 | J72: 226.75 | K72: =G72/360*30 -> 581.58333 | L72: 310 | M72: =K72-L72 -> 271.58333 | N72: =SUMIFS('Leave Tracker'!F:F,'Leave Tracker'!A:A,'Annual Leave Balance'!A72,'Leave Tracker'!C:C,"Annual Leave") -> 0 | O72: =M72-N72 -> 271.58333
A73: 1087 | B73: Aneesh Jose | C73: CCL Supervisor | D73: 40615 | E73: =TODAY() -> 46195 | F73: =E73-D73 -> 5580 | G73: =F73-(H73+I73) -> 5344 | H73: 236 | I73: 0 | J73: 51.5 | K73: =G73/360*30 -> 445.33333 | L73: 349 | M73: =K73-L73 -> 96.333333 | N73: 30 | O73: =M73-N73 -> 66.333333
A74: 1090 | B74: Ashraful Alam Jalil Sheikh | C74: Rewinding Operator | D74: 41017 | E74: 45988 | F74: =E74-D74 -> 4971 | G74: =F74-(H74+I74) -> 4738 | H74: 223 | I74: 10 | J74: 36.25 | K74: =G74/360*30 -> 394.83333 | L74: 331 | M74: =K74-L74 -> 63.833333 | N74: =SUMIFS('Leave Tracker'!F:F,'Leave Tracker'!A:A,'Annual Leave Balance'!A74,'Leave Tracker'!C:C,"Annual Leave") -> 62 | O74: =M74-N74 -> 1.8333333
A75: 1093 | B75: Rafiqul Islam Abu Bakkar | C75: Finish Coating operator | D75: 40829 | E75: =TODAY() -> 46195 | F75: =E75-D75 -> 5366 | G75: =F75-(H75+I75) -> 5242 | H75: 124 | I75: 0 | J75: 92 | K75: =G75/360*30 -> 436.83333 | L75: 300 | M75: =K75-L75 -> 136.83333 | N75: =SUMIFS('Leave Tracker'!F:F,'Leave Tracker'!A:A,'Annual Leave Balance'!A75,'Leave Tracker'!C:C,"Annual Leave") -> 60 | O75: =M75-N75 -> 76.833333
A76: 1106 | B76: Ram Chandra Pradhan | C76: Coating Operator | D76: 41582 | E76: =TODAY() -> 46195 | F76: =E76-D76 -> 4613 | G76: =F76-(H76+I76) -> 4441 | H76: 172 | I76: 0 | J76: 85.25 | K76: =G76/360*30 -> 370.08333 | L76: 240 | M76: =K76-L76 -> 130.08333 | N76: =SUMIFS('Leave Tracker'!F:F,'Leave Tracker'!A:A,'Annual Leave Balance'!A76,'Leave Tracker'!C:C,"Annual Leave") -> 60 | O76: =M76-N76 -> 70.083333
A77: 1109 | B77: Hardev Singh | C77: Forklift Operator | D77: 42742 | E77: =TODAY() -> 46195 | F77: =E77-D77 -> 3453 | G77: =F77-(H77+I77) -> 3241 | H77: 140 | I77: 72 | J77: 0.25 | K77: =G77/360*30 -> 270.08333 | L77: 225 | M77: =K77-L77 -> 45.083333 | N77: =SUMIFS('Leave Tracker'!F:F,'Leave Tracker'!A:A,'Annual Leave Balance'!A77,'Leave Tracker'!C:C,"Annual Leave") -> 0 | O77: =M77-N77 -> 45.083333
A78: 1183 | B78: Safdar Hussain Muhammad Raheem | C78: Helper | D78: 41694 | E78: =TODAY() -> 46195 | F78: =E78-D78 -> 4501 | G78: =F78-(H78+I78) -> 4443 | H78: 58 | I78: 0 | J78: 75.416667 | K78: =G78/360*30 -> 370.25 | L78: 250 | M78: =K78-L78 -> 120.25 | N78: =SUMIFS('Leave Tracker'!F:F,'Leave Tracker'!A:A,'Annual Leave Balance'!A78,'Leave Tracker'!C:C,"Annual Leave") -> 0 | O78: =M78-N78 -> 120.25
A79: 1186 | B79: Israr Ahmed Bashir Ahmed | C79: Assistant Entry Operator | D79: 41694 | E79: =TODAY() -> 46195 | F79: =E79-D79 -> 4501 | G79: =F79-(H79+I79) -> 4409 | H79: 31 | I79: 61 | J79: 82.583333 | K79: =G79/360*30 -> 367.41667 | L79: 240 | M79: =K79-L79 -> 127.41667 | N79: =SUMIFS('Leave Tracker'!F:F,'Leave Tracker'!A:A,'Annual Leave Balance'!A79,'Leave Tracker'!C:C,"Annual Leave") -> 62 | O79: =M79-N79 -> 65.416667
A80: 1194 | B80: Ravi Pal Singh | C80: Entry Helper | D80: 41707 | E80: =TODAY() -> 46195 | F80: =E80-D80 -> 4488 | G80: =F80-(H80+I80) -> 4351 | H80: 117 | I80: 20 | J80: 77.75 | K80: =G80/360*30 -> 362.58333 | L80: 240 | M80: =K80-L80 -> 122.58333 | N80: =SUMIFS('Leave Tracker'!F:F,'Leave Tracker'!A:A,'Annual Leave Balance'!A80,'Leave Tracker'!C:C,"Annual Leave") -> 90 | O80: =M80-N80 -> 32.583333
A81: 1206 | B81: Muhammad Saleem Muhammad Asghar | C81: Helper | D81: 41735 | E81: =TODAY() -> 46195 | F81: =E81-D81 -> 4460 | G81: =F81-(H81+I81) -> 4394 | H81: 66 | I81: 0 | J81: 81.333333 | K81: =G81/360*30 -> 366.16667 | L81: 240 | M81: =K81-L81 -> 126.16667 | N81: =SUMIFS('Leave Tracker'!F:F,'Leave Tracker'!A:A,'Annual Leave Balance'!A81,'Leave Tracker'!C:C,"Annual Leave") -> 60 | O81: =M81-N81 -> 66.166667
A82: 1207 | B82: Muhammad Altaf Khan Muhammad Roshan | C82: Plant Operator | D82: 41735 | E82: =TODAY() -> 46195 | F82: =E82-D82 -> 4460 | G82: =F82-(H82+I82) -> 4367 | H82: 93 | I82: 0 | J82: 63.083333 | K82: =G82/360*30 -> 363.91667 | L82: 256 | M82: =K82-L82 -> 107.91667 | N82: =SUMIFS('Leave Tracker'!F:F,'Leave Tracker'!A:A,'Annual Leave Balance'!A82,'Leave Tracker'!C:C,"Annual Leave") -> 0 | O82: =M82-N82 -> 107.91667
A83: 1208 | B83: Santosh Kumar Tivari | C83: Plant Operator | D83: 41738 | E83: =TODAY() -> 46195 | F83: =E83-D83 -> 4457 | G83: =F83-(H83+I83) -> 4421 | H83: 36 | I83: 0 | J83: 113.58333 | K83: =G83/360*30 -> 368.41667 | L83: 210 | M83: =K83-L83 -> 158.41667 | N83: =SUMIFS('Leave Tracker'!F:F,'Leave Tracker'!A:A,'Annual Leave Balance'!A83,'Leave Tracker'!C:C,"Annual Leave") -> 0 | O83: =M83-N83 -> 158.41667
A84: 1219 | B84: Azam Qureshi Mohammed | C84: Admin Executive | D84: 41770 | E84: =TODAY() -> 46195 | F84: =E84-D84 -> 4425 | G84: =F84-(H84+I84) -> 4253 | H84: 167 | I84: 5 | J84: 34.583333 | K84: =G84/360*30 -> 354.41667 | L84: 275 | M84: =K84-L84 -> 79.416667 | N84: =SUMIFS('Leave Tracker'!F:F,'Leave Tracker'!A:A,'Annual Leave Balance'!A84,'Leave Tracker'!C:C,"Annual Leave") -> 30 | O84: =M84-N84 -> 49.416667
A85: 1220 | B85: Tufail Khan Kamin Shah | C85: Helper | D85: 41770 | E85: =TODAY() -> 46195 | F85: =E85-D85 -> 4425 | G85: =F85-(H85+I85) -> 4124 | H85: 301 | I85: 0 | J85: 79.833333 | K85: =G85/360*30 -> 343.66667 | L85: 219 | M85: =K85-L85 -> 124.66667 | N85: =SUMIFS('Leave Tracker'!F:F,'Leave Tracker'!A:A,'Annual Leave Balance'!A85,'Leave Tracker'!C:C,"Annual Leave") -> 60 | O85: =M85-N85 -> 64.666667
A86: 1221 | B86: Amarnath Kundan | C86: Helper | D86: 41777 | E86: =TODAY() -> 46195 | F86: =E86-D86 -> 4418 | G86: =F86-(H86+I86) -> 4311 | H86: 107 | I86: 0 | J86: 74.416667 | K86: =G86/360*30 -> 359.25 | L86: 240 | M86: =K86-L86 -> 119.25 | N86: =SUMIFS('Leave Tracker'!F:F,'Leave Tracker'!A:A,'Annual Leave Balance'!A86,'Leave Tracker'!C:C,"Annual Leave") -> 60 | O86: =M86-N86 -> 59.25
A87: 1263 | B87: Unni Chuttakatt | C87: IT Manager | D87: 41863 | E87: =TODAY() -> 46195 | F87: =E87-D87 -> 4332 | G87: =F87-(H87+I87) -> 4299 | H87: 33 | I87: 0 | J87: 7.25 | K87: =G87/360*30 -> 358.25 | L87: 298 | M87: =K87-L87 -> 60.25 | N87: 11 | O87: =M87-N87 -> 49.25 | P87: Thousef received mail regading the prior approval for extended days
A88: 1282 | B88: Amrik Suman | C88: Office Boy | D88: 41892 | E88: =TODAY() -> 46195 | F88: =E88-D88 -> 4303 | G88: =F88-(H88+I88) -> 4197 | H88: 106 | I88: 0 | J88: 64.916667 | K88: =G88/360*30 -> 349.75 | L88: 240 | M88: =K88-L88 -> 109.75 | N88: =SUMIFS('Leave Tracker'!F:F,'Leave Tracker'!A:A,'Annual Leave Balance'!A88,'Leave Tracker'!C:C,"Annual Leave") -> 70 | O88: =M88-N88 -> 39.75
A89: 1307 | B89: Praveen Prakash Noha | C89: Operator | D89: 41913 | E89: =TODAY() -> 46195 | F89: =E89-D89 -> 4282 | G89: =F89-(H89+I89) -> 4189 | H89: 78 | I89: 15 | J89: 42.25 | K89: =G89/360*30 -> 349.08333 | L89: 262 | M89: =K89-L89 -> 87.083333 | N89: =SUMIFS('Leave Tracker'!F:F,'Leave Tracker'!A:A,'Annual Leave Balance'!A89,'Leave Tracker'!C:C,"Annual Leave") -> 0 | O89: =M89-N89 -> 87.083333
A90: 1315 | B90: Amarjeet Raja Ram | C90: Helper | D90: 41921 | E90: =TODAY() -> 46195 | F90: =E90-D90 -> 4274 | G90: =F90-(H90+I90) -> 4175 | H90: 99 | I90: 0 | J90: 62.083333 | K90: =G90/360*30 -> 347.91667 | L90: 241 | M90: =K90-L90 -> 106.91667 | N90: =SUMIFS('Leave Tracker'!F:F,'Leave Tracker'!A:A,'Annual Leave Balance'!A90,'Leave Tracker'!C:C,"Annual Leave") -> 26 | O90: =M90-N90 -> 80.916667
A91: 1319 | B91: Mohammed Ziyauddin Shaikh‎ | C91: Area Manager | D91: 41926 | E91: =TODAY() -> 46195 | F91: =E91-D91 -> 4269 | G91: =F91-(H91+I91) -> 4243 | H91: 9 | I91: 17 | J91: 25.75 | K91: =G91/360*30 -> 353.58333 | L91: 283 | M91: =K91-L91 -> 70.583333 | N91: =SUMIFS('Leave Tracker'!F:F,'Leave Tracker'!A:A,'Annual Leave Balance'!A91,'Leave Tracker'!C:C,"Annual Leave") -> 27 | O91: =M91-N91 -> 43.583333
A92: 1345 | B92: Vasanth Kishore Attota | C92: Managing Director | D92: 41594 | E92: =TODAY() -> 46195 | F92: =E92-D92 -> 4601 | G92: =F92-(H92+I92) -> 4614 | H92: -13 | I92: 0 | J92: 254.66667 | K92: =G92/360*30 -> 384.5 | L92: 85 | M92: =K92-L92 -> 299.5 | N92: =SUMIFS('Leave Tracker'!F:F,'Leave Tracker'!A:A,'Annual Leave Balance'!A92,'Leave Tracker'!C:C,"Annual Leave") -> 0 | O92: =M92-N92 -> 299.5
A93: 1360 | B93: Buchi Babu Daram | C93: Production Manager | D93: 41997 | E93: =TODAY() -> 46195 | F93: =E93-D93 -> 4198 | G93: =F93-(H93+I93) -> 4190 | H93: 1 | I93: 7 | J93: 172.33333 | K93: =G93/360*30 -> 349.16667 | L93: 132 | M93: =K93-L93 -> 217.16667 | N93: =SUMIFS('Leave Tracker'!F:F,'Leave Tracker'!A:A,'Annual Leave Balance'!A93,'Leave Tracker'!C:C,"Annual Leave") -> 15 | O93: =M93-N93 -> 202.16667
A94: 1376 | B94: Vishnu Mohanan | C94: Coating Operator | D94: 42054 | E94: =TODAY() -> 46195 | F94: =E94-D94 -> 4141 | G94: =F94-(H94+I94) -> 4075 | H94: 66 | I94: 0 | J94: 63.75 | K94: =G94/360*30 -> 339.58333 | L94: 231 | M94: =K94-L94 -> 108.58333 | N94: =SUMIFS('Leave Tracker'!F:F,'Leave Tracker'!A:A,'Annual Leave Balance'!A94,'Leave Tracker'!C:C,"Annual Leave") -> 60 | O94: =M94-N94 -> 48.583333
A95: 1399 | B95: Bachittar Singh | C95: Forklift Operator | D95: 42085 | E95: =TODAY() -> 46195 | F95: =E95-D95 -> 4110 | G95: =F95-(H95+I95) -> 3802 | H95: =222+14+41 -> 277 | I95: =9+7+15 -> 31 | J95: 38.416667 | K95: =G95/360*30 -> 316.83333 | L95: 240 | M95: =K95-L95 -> 76.833333 | N95: =SUMIFS('Leave Tracker'!F:F,'Leave Tracker'!A:A,'Annual Leave Balance'!A95,'Leave Tracker'!C:C,"Annual Leave") -> 0 | O95: =M95-N95 -> 76.833333
A96: 1402 | B96: Khushali Bhagirath | C96: FR Igglo Helper Line 3 | D96: 42089 | E96: =TODAY() -> 46195 | F96: =E96-D96 -> 4106 | G96: =F96-(H96+I96) -> 4061 | H96: 45 | I96: 0 | J96: 53.583333 | K96: =G96/360*30 -> 338.41667 | L96: 240 | M96: =K96-L96 -> 98.416667 | N96: =SUMIFS('Leave Tracker'!F:F,'Leave Tracker'!A:A,'Annual Leave Balance'!A96,'Leave Tracker'!C:C,"Annual Leave") -> 0 | O96: =M96-N96 -> 98.416667
A97: 1417 | B97: Nawab Afaque Mohammed Khan | C97: Internal Auditor | D97: 42120 | E97: =TODAY() -> 46195 | F97: =E97-D97 -> 4075 | G97: =F97-(H97+I97) -> 3996 | H97: 79 | I97: 0 | J97: 72.166667 | K97: =G97/360*30 -> 333 | L97: 216 | M97: =K97-L97 -> 117 | N97: =SUMIFS('Leave Tracker'!F:F,'Leave Tracker'!A:A,'Annual Leave Balance'!A97,'Leave Tracker'!C:C,"Annual Leave") -> 79 | O97: =M97-N97 -> 38
A98: 1539 | B98: Salahudheen Karikuzhiyan Variyath | C98: Light Vehicle/Bus Driver - Yaris 82330 | D98: 42260 | E98: 46022 | F98: =E98-D98 -> 3762 | G98: =F98-(H98+I98) -> 3648 | H98: 114 | I98: 0 | J98: 32.583333 | K98: =G98/360*30 -> 304 | L98: 241 | M98: =K98-L98 -> 63 | N98: =SUMIFS('Leave Tracker'!F:F,'Leave Tracker'!A:A,'Annual Leave Balance'!A98,'Leave Tracker'!C:C,"Annual Leave") -> 31 | O98: =M98-N98 -> 32
A99: 1544 | B99: Sanjay Kumar Kamala Prasad | C99: Helper | D99: 42261 | E99: =TODAY() -> 46195 | F99: =E99-D99 -> 3934 | G99: =F99-(H99+I99) -> 3831 | H99: 103 | I99: 0 | J99: 94.416667 | K99: =G99/360*30 -> 319.25 | L99: 180 | M99: =K99-L99 -> 139.25 | N99: =SUMIFS('Leave Tracker'!F:F,'Leave Tracker'!A:A,'Annual Leave Balance'!A99,'Leave Tracker'!C:C,"Annual Leave") -> 60 | O99: =M99-N99 -> 79.25
A100: 1570 | B100: Chandra Mohan | C100: Personal Assistant to Deputy Chairperson | D100: 42125 | E100: =TODAY() -> 46195 | F100: =E100-D100 -> 4070 | G100: =F100-(H100+I100) -> 4070 | H100: 0 | I100: 0 | J100: 0 | K100: =G100/360*30 -> 339.16667 | L100: 0 | M100: =K100-L100 -> 339.16667 | N100: =SUMIFS('Leave Tracker'!F:F,'Leave Tracker'!A:A,'Annual Leave Balance'!A100,'Leave Tracker'!C:C,"Annual Leave") -> 0 | O100: =M100-N100 -> 339.16667
A101: 1605 | B101: Manoj Indika Kelum Mahingoda Mahingoda Naidelage | C101: Security Guard | D101: 42439 | E101: =TODAY() -> 46195 | F101: =E101-D101 -> 3756 | G101: =F101-(H101+I101) -> 3722 | H101: 16 | I101: 18 | J101: 55.333333 | K101: =G101/360*30 -> 310.16667 | L101: 210 | M101: =K101-L101 -> 100.16667 | N101: =SUMIFS('Leave Tracker'!F:F,'Leave Tracker'!A:A,'Annual Leave Balance'!A101,'Leave Tracker'!C:C,"Annual Leave") -> 60 | O101: =M101-N101 -> 40.166667
A102: 1608 | B102: Fayaz Ali Mohammed | C102: Marketing Manager | D102: 42449 | E102: =TODAY() -> 46195 | F102: =E102-D102 -> 3746 | G102: =F102-(H102+I102) -> 3720 | H102: 26 | I102: 0 | J102: 65.166667 | K102: =G102/360*30 -> 310 | L102: 200 | M102: =K102-L102 -> 110 | N102: =SUMIFS('Leave Tracker'!F:F,'Leave Tracker'!A:A,'Annual Leave Balance'!A102,'Leave Tracker'!C:C,"Annual Leave") -> 13 | O102: =M102-N102 -> 97
A103: 1611 | B103: Sunil Rana | C103: Supervisor | D103: 42477 | E103: =TODAY() -> 46195 | F103: =E103-D103 -> 3718 | G103: =F103-(H103+I103) -> 3686 | H103: 32 | I103: 0 | J103: 109.33333 | K103: =G103/360*30 -> 307.16667 | L103: 153 | M103: =K103-L103 -> 154.16667 | N103: =SUMIFS('Leave Tracker'!F:F,'Leave Tracker'!A:A,'Annual Leave Balance'!A103,'Leave Tracker'!C:C,"Annual Leave") -> 39 | O103: =M103-N103 -> 115.16667
A104: 1617 | B104: Mohammed Mubeen Mahmood Ali | C104: Sr. HSE Officer | D104: 42519 | E104: =TODAY() -> 46195 | F104: =E104-D104 -> 3676 | G104: =F104-(H104+I104) -> 3645 | H104: 31 | I104: 0 | J104: 45.416667 | K104: =G104/360*30 -> 303.75 | L104: 226 | M104: =K104-L104 -> 77.75 | N104: =SUMIFS('Leave Tracker'!F:F,'Leave Tracker'!A:A,'Annual Leave Balance'!A104,'Leave Tracker'!C:C,"Annual Leave") -> 18 | O104: =M104-N104 -> 59.75
A105: 1648 | B105: Arbab Ahmed Khan | C105: CEO | D105: 42614 | E105: =TODAY() -> 46195 | F105: =E105-D105 -> 3581 | G105: =F105-(H105+I105) -> 3601 | H105: -21 | I105: 1 | J105: 180.25 | K105: =G105/360*30 -> 300.08333 | L105: 75 | M105: =K105-L105 -> 225.08333 | N105: =SUMIFS('Leave Tracker'!F:F,'Leave Tracker'!A:A,'Annual Leave Balance'!A105,'Leave Tracker'!C:C,"Annual Leave") -> 0 | O105: =M105-N105 -> 225.08333
A106: 1654 | B106: Nehal Ahamad Najirullah | C106: Aluminium Fabricator | D106: 42670 | E106: =TODAY() -> 46195 | F106: =E106-D106 -> 3525 | G106: =F106-(H106+I106) -> 3489 | H106: 11 | I106: 25 | J106: 77.916667 | K106: =G106/360*30 -> 290.75 | L106: 168 | M106: =K106-L106 -> 122.75 | N106: =SUMIFS('Leave Tracker'!F:F,'Leave Tracker'!A:A,'Annual Leave Balance'!A106,'Leave Tracker'!C:C,"Annual Leave") -> 30 | O106: =M106-N106 -> 92.75
A107: 1693 | B107: Shaik Rasheed Ahmed | C107: Site Engineer | D107: 42694 | E107: =TODAY() -> 46195 | F107: =E107-D107 -> 3501 | G107: =F107-(H107+I107) -> 3488 | H107: 13 | I107: 0 | J107: 98.833333 | K107: =G107/360*30 -> 290.66667 | L107: 147 | M107: =K107-L107 -> 143.66667 | N107: =SUMIFS('Leave Tracker'!F:F,'Leave Tracker'!A:A,'Annual Leave Balance'!A107,'Leave Tracker'!C:C,"Annual Leave") -> 0 | O107: =M107-N107 -> 143.66667
A108: 1699 | B108: Rejanesh Kumar Raghavan | C108: CNC Programmer cum Operator | D108: 42698 | E108: =TODAY() -> 46195 | F108: =E108-D108 -> 3497 | G108: =F108-(H108+I108) -> 3471 | H108: 14 | I108: 12 | J108: 107.41667 | K108: =G108/360*30 -> 289.25 | L108: 137 | M108: =K108-L108 -> 152.25 | N108: =SUMIFS('Leave Tracker'!F:F,'Leave Tracker'!A:A,'Annual Leave Balance'!A108,'Leave Tracker'!C:C,"Annual Leave") -> 61 | O108: =M108-N108 -> 91.25
A109: 1708 | B109: Nakul Terasi | C109: Helper | D109: 42716 | E109: =TODAY() -> 46195 | F109: =E109-D109 -> 3479 | G109: =F109-(H109+I109) -> 3464 | H109: 15 | I109: 0 | J109: 62.833333 | K109: =G109/360*30 -> 288.66667 | L109: 181 | M109: =K109-L109 -> 107.66667 | N109: =SUMIFS('Leave Tracker'!F:F,'Leave Tracker'!A:A,'Annual Leave Balance'!A109,'Leave Tracker'!C:C,"Annual Leave") -> 60 | O109: =M109-N109 -> 47.666667
A110: 1730 | B110: Wenjing Zhang | C110: Sourcing & Quality Coordinator | D110: 42767 | E110: =TODAY() -> 46195 | F110: =E110-D110 -> 3428 | G110: =F110-(H110+I110) -> 3428 | H110: 0 | I110: 0 | J110: 0 | K110: =G110/360*30 -> 285.66667 | L110: 0 | M110: =K110-L110 -> 285.66667 | N110: =SUMIFS('Leave Tracker'!F:F,'Leave Tracker'!A:A,'Annual Leave Balance'!A110,'Leave Tracker'!C:C,"Annual Leave") -> 0 | O110: =M110-N110 -> 285.66667
... A122: 2078 | B122: Jabeena Ponmanichi Baboo | C122: Accounts Manager | D122: 43140 | E122: =TODAY() -> 46195 | F122: =E122-D122 -> 3055 | G122: =F122-(H122+I122) -> 3045 | H122: 10 | I122: 0 | J122: 125.91667 | K122: =G122/360*30 -> 253.75 | L122: 83 | M122: =K122-L122 -> 170.75 | N122: =SUMIFS('Leave Tracker'!F:F,'Leave Tracker'!A:A,'Annual Leave Balance'!A122,'Leave Tracker'!C:C,"Annual Leave") -> 40 | O122: =M122-N122 -> 130.75
A123: 2120 | B123: Siraj Ahmad | C123: Operator | D123: 43206 | E123: =TODAY() -> 46195 | F123: =E123-D123 -> 2989 | G123: =F123-(H123+I123) -> 2978 | H123: 11 | I123: 0 | J123: 22.333333 | K123: =G123/360*30 -> 248.16667 | L123: 181 | M123: =K123-L123 -> 67.166667 | N123: 10 | O123: =M123-N123 -> 57.166667
...
